{"<OOV>": 1, "shopee": 2, "nya": 3, "bagus": 4, "belanja": 5, "ongkir": 6, "yg": 7, "barang": 8, "mantap": 9, "aplikasi": 10, "gak": 11, "gratis": 12, "banget": 13, "membantu": 14, "mahal": 15, "ga": 16, "ya": 17, "iklan": 18, "12": 19, "udah": 20, "suka": 21, "aja": 22, "ok": 23, "pengiriman": 24, "tolong": 25, "good": 26, "cepat": 27, "apk": 28, "kasih": 29, "gk": 30, "beli": 31, "puas": 32, "sesuai": 33, "mudah": 34, "kecewa": 35, "pake": 36, "ongkirnya": 37, "murah": 38, "oke": 39, "harga": 40, "bayar": 41, "hp": 42, "shope": 43, "toko": 44, "shoppe": 45, "semoga": 46, "pas": 47, "akun": 48, "muncul": 49, "sih": 50, "keren": 51, "voucher": 52, "udh": 53, "bintang": 54, "d": 55, "online": 56, "paket": 57, "pesanan": 58, "masuk": 59, "kalo": 60, "lemot": 61, "bgt": 62, "diskon": 63, "penjual": 64, "memuaskan": 65, "cod": 66, "promo": 67, "terima": 68, "buka": 69, "kali": 70, "sy": 71, "5": 72, "pakai": 73, "bikin": 74, "buruk": 75, "kirim": 76, "kurir": 77, "mohon": 78, "susah": 79, "1": 80, "mengganggu": 81, "jasa": 82, "update": 83, "terbaik": 84, "amanah": 85, "produk": 86, "min": 87, "jaringan": 88, "shoope": 89, "ribet": 90, "pesan": 91, "2": 92, "top": 93, "biaya": 94, "pelayanan": 95, "tdk": 96, "aplikasinya": 97, "kaya": 98, "tp": 99, "karna": 100, "orang": 101, "dah": 102, "gimana": 103, "pokoknya": 104, "terimakasih": 105, "aman": 106, "cek": 107, "0": 108, "lagi": 109, "lumayan": 110, "no": 111, "trus": 112, "klo": 113, "gitu": 114, "fitur": 115, "sale": 116, "gua": 117, "spx": 118, "jelek": 119, "koin": 120, "kesini": 121, "saya": 122, "download": 123, "kebutuhan": 124, "berbelanja": 125, "dana": 126, "jg": 127, "gw": 128, "uang": 129, "biar": 130, "dgn": 131, "senang": 132, "mengecewakan": 133, "aneh": 134, "deh": 135, "best": 136, "shop": 137, "sukses": 138, "perbaiki": 139, "ini": 140, "tgl": 141, "login": 142, "tau": 143, "lancar": 144, "3": 145, "si": 146, "kadang": 147, "cuman": 148, "game": 149, "saldo": 150, "pembayaran": 151, "kena": 152, "ku": 153, "video": 154, "nunggu": 155, "spaylater": 156, "g": 157, "nyaman": 158, "potongan": 159, "pembeli": 160, "konsumen": 161, "lengkap": 162, "gini": 163, "out": 164, "sya": 165, "lg": 166, "pdhl": 167, "the": 168, "\ud83d\udc4d": 169, "tiktok": 170, "eh": 171, "flash": 172, "mulu": 173, "terus": 174, "pay": 175, "hilang": 176, "seller": 177, "baik": 178, "limit": 179, "berat": 180, "mempermudah": 181, "ribu": 182, "kak": 183, "hapus": 184, "pelit": 185, "lu": 186, "langsung": 187, "live": 188, "gabisa": 189, "alamat": 190, "lambat": 191, "lazada": 192, "emang": 193, "harganya": 194, "bgus": 195, "doang": 196, "jd": 197, "sebelah": 198, "ni": 199, "enak": 200, "000": 201, "jelas": 202, "hadiah": 203, "bener": 204, "pelanggan": 205, "alhamdulillah": 206, "maaf": 207, "barangnya": 208, "tpi": 209, "sekali": 210, "skrg": 211, "padahal": 212, "penipuan": 213, "jual": 214, "pesen": 215, "dpt": 216, "dan": 217, "penanganan": 218, "pengguna": 219, "mending": 220, "ny": 221, "co": 222, "paylater": 223, "lgi": 224, "data": 225, "blm": 226, "tapi": 227, "shopeepay": 228, "males": 229, "lelet": 230, "sdh": 231, "baguss": 232, "dapet": 233, "parah": 234, "kayak": 235, "telat": 236, "event": 237, "nggak": 238, "kualitas": 239, "dri": 240, "berguna": 241, "hemat": 242, "bagusss": 243, "utk": 244, "menyenangkan": 245, "banyak": 246, "diperbaiki": 247, "salah": 248, "nggk": 249, "gagal": 250, "pokok": 251, "sopi": 252, "sampe": 253, "bisa": 254, "seabank": 255, "tetep": 256, "kek": 257, "jdi": 258, "admin": 259, "e": 260, "iklannya": 261, "blokir": 262, "dulu": 263, "rumah": 264, "m": 265, "mantul": 266, "log": 267, "app": 268, "skrng": 269, "jualan": 270, "mantab": 271, "gampang": 272, "nih": 273, "jaya": 274, "\ud83d\ude4f": 275, "terpercaya": 276, "pengirimannya": 277, "cepet": 278, "bermanfaat": 279, "habis": 280, "spinjam": 281, "pindah": 282, "4": 283, "tanggal": 284, "layanan": 285, "batalin": 286, "makasih": 287, "tingkatkan": 288, "menarik": 289, "ganggu": 290, "order": 291, "tokopedia": 292, "sampai": 293, "proses": 294, "an": 295, "lama": 296, "rp": 297, "knp": 298, "yaa": 299, "ttp": 300, "penipu": 301, "sangat": 302, "kemarin": 303, "bantu": 304, "expedisi": 305, "jam": 306, "memudahkan": 307, "ngk": 308, "error": 309, "shoopee": 310, "cs": 311, "juga": 312, "cari": 313, "kerja": 314, "pilihan": 315, "indonesia": 316, "eror": 317, "bnyk": 318, "tolak": 319, "k": 320, "l": 321, "tiba2": 322, "in": 323, "msh": 324, "notif": 325, "tutup": 326, "otomatis": 327, "terjangkau": 328, "job": 329, "bug": 330, "shopeee": 331, "y": 332, "ramah": 333, "ganti": 334, "dlu": 335, "shopy": 336, "itu": 337, "isi": 338, "sistem": 339, "ngak": 340, "nice": 341, "50": 342, "jos": 343, "shoppee": 344, "kau": 345, "semenjak": 346, "kuota": 347, "ad": 348, "via": 349, "transaksi": 350, "tuh": 351, "up": 352, "2023": 353, "ko": 354, "sekarang": 355, "menggangu": 356, "x": 357, "instal": 358, "bos": 359, "blnja": 360, "n": 361, "kembalikan": 362, "later": 363, "kurirnya": 364, "verifikasi": 365, "jarang": 366, "nomor": 367, "dipake": 368, "i": 369, "blanja": 370, "liat": 371, "bngt": 372, "duit": 373, "klik": 374, "7": 375, "giliran": 376, "shopi": 377, "masak": 378, "anak": 379, "yah": 380, "sma": 381, "tagihan": 382, "slalu": 383, "main": 384, "lag": 385, "coba": 386, "menu": 387, "ama": 388, "email": 389, "minggu": 390, "mu": 391, "10": 392, "express": 393, "minimal": 394, "cocok": 395, "respon": 396, "\ud83d\udc4d\ud83d\udc4d\ud83d\udc4d": 397, "kebanyakan": 398, "rupiah": 399, "ukuran": 400, "ekspedisi": 401, "pengembalian": 402, "bank": 403, "om": 404, "pembelian": 405, "estimasi": 406, "pertahankan": 407, "beda": 408, "pke": 409, "lo": 410, "mencari": 411, "ngapain": 412, "kesel": 413, "bnyak": 414, "dll": 415, "terbantu": 416, "sgt": 417, "menipu": 418, "kode": 419, "maju": 420, "hati": 421, "dishopee": 422, "payah": 423, "sinyal": 424, "dikit": 425, "food": 426, "chat": 427, "rugi": 428, "trs": 429, "tujuan": 430, "pelayanannya": 431, "kedepannya": 432, "transfer": 433, "aktifkan": 434, "berkurang": 435, "indomaret": 436, "kan": 437, "ngelag": 438, "kota": 439, "8": 440, "jgn": 441, "make": 442, "saja": 443, "merugikan": 444, "uda": 445, "paketnya": 446, "customer": 447, "aktivitas": 448, "mobil": 449, "komisi": 450, "sayang": 451, "pengalaman": 452, "km": 453, "p": 454, "non": 455, "pribadi": 456, "uninstal": 457, "sm": 458, "t": 459, "kya": 460, "simple": 461, "20": 462, "ditolak": 463, "dibatasi": 464, "free": 465, "milih": 466, "q": 467, "langganan": 468, "palsu": 469, "tolol": 470, "saran": 471, "30": 472, "dipesan": 473, "pilih": 474, "negeri": 475, "rusak": 476, "mantapp": 477, "keranjang": 478, "dipakai": 479, "tlp": 480, "tim": 481, "ulang": 482, "klau": 483, "dikirim": 484, "lah": 485, "woy": 486, "\ud83d\ude01": 487, "you": 488, "sllu": 489, "butuh": 490, "apa": 491, "mntap": 492, "krna": 493, "rb": 494, "kasi": 495, "ngeleg": 496, "dr": 497, "smpe": 498, "gambar": 499, "tinggal": 500, "org": 501, "praktis": 502, "krn": 503, "nyampe": 504, "gangguan": 505, "hari": 506, "pinjam": 507, "dlm": 508, "diskonnya": 509, "j": 510, "aktif": 511, "mantep": 512, "kendala": 513, "pakek": 514, "dg": 515, "cekout": 516, "status": 517, "check": 518, "wajah": 519, "terbaru": 520, "gila": 521, "tipu": 522, "lbih": 523, "ayo": 524, "daftar": 525, "keperluan": 526, "diantar": 527, "mager": 528, "malas": 529, "dibuka": 530, "ongkos": 531, "dijual": 532, "auto": 533, "unistal": 534, "pdhal": 535, "asli": 536, "tidak": 537, "kemaren": 538, "stop": 539, "bermasalah": 540, "menang": 541, "ngapa": 542, "untung": 543, "penjualnya": 544, "byk": 545, "thanks": 546, "shoppy": 547, "otp": 548, "ajah": 549, "birthday": 550, "knpa": 551, "ngasih": 552, "sendiri": 553, "u": 554, "driver": 555, "buyer": 556, "wa": 557, "seru": 558, "tf": 559, "stabil": 560, "niat": 561, "pembatalan": 562, "apl": 563, "ada": 564, "bangett": 565, "iya": 566, "juta": 567, "\ud83d\udc4d\ud83d\udc4d\ud83d\udc4d\ud83d\udc4d\ud83d\udc4d": 568, "loading": 569, "di": 570, "selesai": 571, "sulit": 572, "pulsa": 573, "pokonya": 574, "cashback": 575, "terjamin": 576, "orderan": 577, "semua": 578, "asu": 579, "nambah": 580, "makanan": 581, "gede": 582, "service": 583, "alfa": 584, "biasa": 585, "sophee": 586, "bilangnya": 587, "link": 588, "ngga": 589, "trimakasih": 590, "dihapus": 591, "tok": 592, "vocer": 593, "menganggu": 594, "brg": 595, "wifi": 596, "hilangkan": 597, "kapok": 598, "alasan": 599, "besar": 600, "bilang": 601, "akurat": 602, "mana": 603, "pesanannya": 604, "bet": 605, "benar2": 606, "lokasi": 607, "sumpah": 608, "expres": 609, "kesal": 610, "banyakin": 611, "pesenan": 612, "lihat": 613, "masyarakat": 614, "kk": 615, "like": 616, "konfirmasi": 617, "mlh": 618, "modal": 619, "1000": 620, "kurangi": 621, "nyari": 622, "gue": 623, "tampilan": 624, "belanjaan": 625, "google": 626, "lupa": 627, "sangat2": 628, "wajar": 629, "install": 630, "2x": 631, "promonya": 632, "allah": 633, "s": 634, "bnget": 635, "biru": 636, "cocoki": 637, "bingung": 638, "sopee": 639, "marketplace": 640, "ter": 641, "13": 642, "sopan": 643, "perbanyak": 644, "200": 645, "diterima": 646, "cape": 647, "kekurangan": 648, "penilaian": 649, "rumit": 650, "tokonya": 651, "layar": 652, "pengantaran": 653, "pinjaman": 654, "tulisan": 655, "tertarik": 656, "nyaa": 657, "pdahal": 658, "sampah": 659, "bs": 660, "love": 661, "rating": 662, "program": 663, "perubahan": 664, "kren": 665, "turun": 666, "mitra": 667, "terkirim": 668, "berkembang": 669, "sedikit": 670, "ngisi": 671, "taik": 672, "deskripsi": 673, "memakai": 674, "sialan": 675, "tingkat": 676, "kemudahan": 677, "bangat": 678, "bertanggung": 679, "tindakan": 680, "vidio": 681, "kalau": 682, "sip": 683, "responnya": 684, "happy": 685, "shopie": 686, "gunakan": 687, "hasil": 688, "disini": 689, "100": 690, "bangettt": 691, "dh": 692, "disuruh": 693, "bonus": 694, "nga": 695, "loh": 696, "ulasan": 697, "scam": 698, "ampun": 699, "mo": 700, "tu": 701, "solusi": 702, "daerah": 703, "clear": 704, "produknya": 705, "nonton": 706, "asuuu": 707, "adminnya": 708, "gmn": 709, "sistemnya": 710, "ksh": 711, "full": 712, "makin": 713, "\ud83d\udc4d\ud83d\udc4d": 714, "kwalitas": 715, "abis": 716, "vulgar": 717, "kn": 718, "very": 719, "\ud83d\udc4d\ud83d\udc4d\ud83d\udc4d\ud83d\udc4d": 720, "shopeefood": 721, "berkah": 722, "iphone": 723, "macet": 724, "jakarta": 725, "bukak": 726, "terkadang": 727, "ngotak": 728, "burik": 729, "ba": 730, "sama": 731, "aamiin": 732, "aj": 733, "mencurigakan": 734, "is": 735, "bsa": 736, "menjual": 737, "kah": 738, "seharian": 739, "berjaya": 740, "dong": 741, "mentang": 742, "aq": 743, "cash": 744, "menit": 745, "gj": 746, "lahh": 747, "keuntungan": 748, "nge": 749, "kl": 750, "ajukan": 751, "akal": 752, "foto": 753, "bakar": 754, "percaya": 755, "kok": 756, "kembar": 757, "iklanya": 758, "kelen": 759, "internet": 760, "naikin": 761, "bergabung": 762, "mkin": 763, "super": 764, "kunjung": 765, "kejadian": 766, "tunggu": 767, "akhir2": 768, "checkout": 769, "jadinya": 770, "umur": 771, "sehat": 772, "banyakan": 773, "dikasih": 774, "aktifin": 775, "kecuali": 776, "ilang": 777, "heran": 778, "500": 779, "terupdate": 780, "fiktif": 781, "layak": 782, "rill": 783, "bner": 784, "murah\u00b2": 785, "discon": 786, "lain": 787, "alias": 788, "and": 789, "nyesel": 790, "ragu": 791, "kenyamanan": 792, "mahall": 793, "mayan": 794, "sperti": 795, "pengajuan": 796, "market": 797, "place": 798, "komplain": 799, "prosesnya": 800, "semangat": 801, "gbs": 802, "mantappp": 803, "dech": 804, "bngtt": 805, "tiba": 806, "dikembalikan": 807, "ajaa": 808, "dibeli": 809, "nama": 810, "lol": 811, "siip": 812, "aturan": 813, "dpet": 814, "perasaan": 815, "terpaksa": 816, "mantaaaap": 817, "cpt": 818, "centang": 819, "hallo": 820, "retur": 821, "membayar": 822, "ngeselin": 823, "30rb": 824, "hub": 825, "gara2": 826, "amin": 827, "wkwk": 828, "penerima": 829, "poin": 830, "shopepay": 831, "php": 832, "qris": 833, "diblokir": 834, "tangga": 835, "pokoke": 836, "sngt": 837, "poll": 838, "pakaian": 839, "perhatikan": 840, "ndak": 841, "\ud83d\ude2d": 842, "voucer": 843, "datengnya": 844, "wajib": 845, "metode": 846, "tambahan": 847, "maps": 848, "\ud83d\ude4f\ud83d\ude4f\ud83d\ude4f": 849, "kecil": 850, "waktu": 851, "kemas": 852, "20rb": 853, "baikk": 854, "dowload": 855, "mengadakan": 856, "haha": 857, "opsi": 858, "thank": 859, "desa": 860, "blok": 861, "bca": 862, "dateng": 863, "nyh": 864, "lh": 865, "of": 866, "menyelesaikan": 867, "tks": 868, "sungguh": 869, "meresahkan": 870, "kecamatan": 871, "la": 872, "ambil": 873, "ori": 874, "stelah": 875, "\ud83d\udc4d\ud83c\udffb": 876, "markotop": 877, "mslh": 878, "3x": 879, "bohong": 880, "suruh": 881, "bget": 882, "dibilang": 883, "30k": 884, "\ud83d\udc4e": 885, "shoppepay": 886, "memori": 887, "toko\u00b2": 888, "paksa": 889, "offline": 890, "membutuhkan": 891, "costumer": 892, "sering": 893, "okee": 894, "jiwa": 895, "sembako": 896, "developer": 897, "toko2": 898, "bagus2": 899, "sangatt": 900, "sebulan": 901, "\ud83d\ude02": 902, "pedagang": 903, "berharap": 904, "responsif": 905, "cache": 906, "alfamart": 907, "payleter": 908, "sempurna": 909, "diupdate": 910, "jadi": 911, "menunggu": 912, "berhari": 913, "aplikasih": 914, "murahh": 915, "efisien": 916, "barang2": 917, "kagak": 918, "janji": 919, "namanya": 920, "lamaa": 921, "secepatnya": 922, "produk\u00b2": 923, "memaksakan": 924, "selalu": 925, "cinta": 926, "sampai2": 927, "limitnya": 928, "sj": 929, "dimana": 930, "batas": 931, "skrang": 932, "usaha": 933, "kepotong": 934, "5k": 935, "beneran": 936, "paham": 937, "sophe": 938, "dn": 939, "man": 940, "skali": 941, "berubah": 942, "memperhatikan": 943, "baca": 944, "box": 945, "batasi": 946, "rekomendasi": 947, "ato": 948, "berhenti": 949, "hrs": 950, "pusing": 951, "apa\u00b2": 952, "notifikasi": 953, "chek": 954, "leled": 955, "knapa": 956, "bli": 957, "kntl": 958, "shopping": 959, "batalkan": 960, "ram": 961, "butuhkan": 962, "hangus": 963, "real": 964, "gajelas": 965, "listrik": 966, "bagussss": 967, "teruss": 968, "kebijakan": 969, "abal2": 970, "ditambah": 971, "uninstall": 972, "tarik": 973, "kyk": 974, "koinnya": 975, "ngambil": 976, "acara": 977, "tis": 978, "persen": 979, "back": 980, "nol": 981, "nomer": 982, "sengaja": 983, "ngadain": 984, "donk": 985, "ka": 986, "diperhatikan": 987, "rate": 988, "kupon": 989, "potong": 990, "hrga": 991, "kocak": 992, "mendukung": 993, "membeli": 994, "5rb": 995, "potongannya": 996, "apapun": 997, "games": 998, "koneksi": 999, "rmh": 1000, "tdak": 1001, "gaes": 1002, "terpotong": 1003, "shpee": 1004, "coy": 1005, "lemott": 1006, "14": 1007, "mengajukan": 1008, "19": 1009, "bgini": 1010, "penanganannya": 1011, "tokped": 1012, "trauma": 1013, "terkesan": 1014, "sea": 1015, "100rb": 1016, "tekan": 1017, "lmm": 1018, "lm": 1019, "garis": 1020, "tambah": 1021, "yakin": 1022, "oren": 1023, "kadang2": 1024, "lari": 1025, "bohongnya": 1026, "dipercaya": 1027, "aslinya": 1028, "sakit": 1029, "w": 1030, "bertambah": 1031, "msih": 1032, "bagusan": 1033, "komplit": 1034, "acc": 1035, "capek": 1036, "smpai": 1037, "za": 1038, "aktiv": 1039, "desember": 1040, "tentukan": 1041, "membela": 1042, "skarang": 1043, "focer": 1044, "goood": 1045, "banh": 1046, "hah": 1047, "syuka": 1048, "akhirnya": 1049, "termurah": 1050, "kartu": 1051, "aku": 1052, "enakan": 1053, "ud": 1054, "semakin": 1055, "dsni": 1056, "posting": 1057, "a": 1058, "b": 1059, "anehnya": 1060, "tanggapan": 1061, "tai": 1062, "bekukan": 1063, "ruang": 1064, "boss": 1065, "spay": 1066, "jngn": 1067, "dtg": 1068, "cmn": 1069, "gold": 1070, "kami": 1071, "shopipay": 1072, "it": 1073, "brang": 1074, "spam": 1075, "untk": 1076, "sll": 1077, "off": 1078, "dj": 1079, "jeli": 1080, "vocher": 1081, "hahaha": 1082, "mengikuti": 1083, "\ud83d\ude0a": 1084, "malem": 1085, "mendadak": 1086, "pencairan": 1087, "xl": 1088, "belom": 1089, "keterlambatan": 1090, "gamenya": 1091, "wanita": 1092, "baju": 1093, "filter": 1094, "by": 1095, "kembali": 1096, "ik": 1097, "puass": 1098, "blnj": 1099, "smp": 1100, "tamat": 1101, "level": 1102, "semogah": 1103, "biyaya": 1104, "pengen": 1105, "permintaan": 1106, "perhatiannya": 1107, "mutu": 1108, "paylaternya": 1109, "diakses": 1110, "tangani": 1111, "besar2": 1112, "hasilnya": 1113, "dpat": 1114, "diakun": 1115, "dibatalkan": 1116, "jadwal": 1117, "cobak": 1118, "memebantu": 1119, "\u2764": 1120, "blom": 1121, "spaylatter": 1122, "bicara": 1123, "memenuhi": 1124, "pekerjaan": 1125, "padah": 1126, "penuh": 1127, "tuhan": 1128, "freya": 1129, "agency": 1130, "desk": 1131, "call": 1132, "ditindak": 1133, "ne": 1134, "\ud83d\ude4f\ud83d\ude4f\ud83d\ude4f\ud83d\ude4f": 1135, "bulanan": 1136, "spayleter": 1137, "mati": 1138, "bekuin": 1139, "team": 1140, "internal": 1141, "wkwkwkwk": 1142, "updet": 1143, "maksa": 1144, "pembelinya": 1145, "berkualitas": 1146, "sampenya": 1147, "me": 1148, "kasian": 1149, "ngiklan": 1150, "skg": 1151, "antarkan": 1152, "molor": 1153, "ngirim": 1154, "lunas": 1155, "topup": 1156, "strategi": 1157, "cust": 1158, "komentar": 1159, "\ud83d\ude2d\ud83d\ude2d": 1160, "menguntungkan": 1161, "gud": 1162, "buffering": 1163, "kerennn": 1164, "suda": 1165, "pembaruan": 1166, "berjalan": 1167, "keluarga": 1168, "tersedia": 1169, "uu": 1170, "sz": 1171, "loko": 1172, "go": 1173, "c": 1174, "sprt": 1175, "pahami": 1176, "tololll": 1177, "apknya": 1178, "bngst": 1179, "bertindak": 1180, "kecurangan": 1181, "suara": 1182, "smoga": 1183, "penghasilan": 1184, "gjls": 1185, "bukanya": 1186, "cakep": 1187, "lainya": 1188, "shopeenya": 1189, "recomend": 1190, "hidup": 1191, "whatsapp": 1192, "error'": 1193, "spyleter": 1194, "480p": 1195, "720p": 1196, "sekaliii": 1197, "gunanya": 1198, "menolak": 1199, "applikasi": 1200, "bang": 1201, "kelain": 1202, "memper": 1203, "recommended": 1204, "punya": 1205, "15": 1206, "16": 1207, "turunin": 1208, "scroll": 1209, "rekening": 1210, "video2": 1211, "merusak": 1212, "penjualan": 1213, "kalah": 1214, "aneh2": 1215, "commerce": 1216, "masi": 1217, "berlaku": 1218, "kecewaaa": 1219, "maklumi": 1220, "cht": 1221, "tiba\u00b2": 1222, "ketentuan": 1223, "mesan": 1224, "kalu": 1225, "kemana": 1226, "anteraja": 1227, "era": 1228, "peringatan": 1229, "lma": 1230, "menikmati": 1231, "guna": 1232, "discount": 1233, "bagussssss": 1234, "bener2": 1235, "bgs": 1236, "versi": 1237, "boong": 1238, "murah2": 1239, "bandingkan": 1240, "aplication": 1241, "problem": 1242, "jawa": 1243, "kesusahan": 1244, "indo": 1245, "otoriter": 1246, "nipu": 1247, "\ud83e\udd70\ud83e\udd70\ud83e\udd70": 1248, "chekout": 1249, "ninja": 1250, "onlen": 1251, "pinjol": 1252, "td": 1253, "\ud83e\udd70": 1254, "mw": 1255, "dibalikin": 1256, "lalot": 1257, "datangnya": 1258, "sihh": 1259, "jengkel": 1260, "handphone": 1261, "harian": 1262, "lama2": 1263, "menghubungi": 1264, "recomended": 1265, "bugnya": 1266, "menerus": 1267, "woi": 1268, "lagii": 1269, "ngebug": 1270, "ajh": 1271, "fiturnya": 1272, "69": 1273, "okay": 1274, "dituduh": 1275, "kon": 1276, "ws": 1277, "apik": 1278, "kaitkn": 1279, "coin": 1280, "mesen": 1281, "jatuh": 1282, "atur": 1283, "dehh": 1284, "\u263a\ufe0f": 1285, "sekalii": 1286, "datang": 1287, "pda": 1288, "chrome": 1289, "jawab": 1290, "smg": 1291, "laris": 1292, "manis": 1293, "aing": 1294, "sekolah": 1295, "teros": 1296, "cm": 1297, "gtatis": 1298, "penguna": 1299, "cok": 1300, "token": 1301, "penukaran": 1302, "tanam": 1303, "normal": 1304, "belajar": 1305, "laporan": 1306, "menawarkan": 1307, "password": 1308, "mengalami": 1309, "rata": 1310, "melulu": 1311, "sesuaii": 1312, "kegiatan": 1313, "abal": 1314, "peralatan": 1315, "gatau": 1316, "alangkah": 1317, "cukup": 1318, "pliss": 1319, "benerin": 1320, "sicepat": 1321, "coret": 1322, "\u2764\u2764\u2764": 1323, "edit": 1324, "mengerti": 1325, "lage": 1326, "6": 1327, "wallet": 1328, "permanen": 1329, "gx": 1330, "mmbantu": 1331, "undian": 1332, "putih": 1333, "okey": 1334, "lipat": 1335, "menangani": 1336, "keluhan": 1337, "bagusnya": 1338, "300": 1339, "plis": 1340, "repot": 1341, "dipotong": 1342, "juara": 1343, "halo": 1344, "packing": 1345, "klaim": 1346, "tingal": 1347, "hehe": 1348, "memaksa": 1349, "awal": 1350, "dikeluarin": 1351, "bru": 1352, "qr": 1353, "khawatir": 1354, "poko": 1355, "lbh": 1356, "cina": 1357, "id": 1358, "5x": 1359, "berkedok": 1360, "bertransaksi": 1361, "loding": 1362, "berulang": 1363, "bri": 1364, "lanjuti": 1365, "aktifitas": 1366, "sehari": 1367, "mlah": 1368, "penonton": 1369, "member": 1370, "ng": 1371, "intinya": 1372, "kepuasan": 1373, "gasuka": 1374, "dikirim2": 1375, "\ud83d\ude0d": 1376, "tenornya": 1377, "bulan": 1378, "kemampuan": 1379, "\u2764\ufe0f\u2764\ufe0f": 1380, "ringan": 1381, "agen": 1382, "nakal": 1383, "melebihi": 1384, "seharga": 1385, "melampaui": 1386, "memuat": 1387, "bego": 1388, "tolonglah": 1389, "gabung": 1390, "3500": 1391, "2500": 1392, "perbarui": 1393, "scrol": 1394, "th": 1395, "diatas": 1396, "thx": 1397, "klu": 1398, "josss": 1399, "malam": 1400, "hacker": 1401, "harap": 1402, "keamanan": 1403, "betulin": 1404, "resto": 1405, "we": 1406, "maen": 1407, "menemukan": 1408, "gilaaa": 1409, "sudah": 1410, "jnt": 1411, "prioritaskan": 1412, "takut": 1413, "pagi": 1414, "iklankan": 1415, "nyebelin": 1416, "balikin": 1417, "depan": 1418, "\ud83d\ude18": 1419, "shopee\ud83d\udc4d": 1420, "tapii": 1421, "dikemas": 1422, "pisan": 1423, "tiktokshop": 1424, "upload": 1425, "hentikan": 1426, "emg": 1427, "baru": 1428, "terhindar": 1429, "oppo": 1430, "keuangan": 1431, "syah": 1432, "buru": 1433, "kiriman": 1434, "ind": 1435, "maret": 1436, "karena": 1437, "smga": 1438, "ngadi": 1439, "mencapai": 1440, "diperkecil": 1441, "menyukai": 1442, "muat": 1443, "seminggu": 1444, "pro": 1445, "sanggat": 1446, "buat": 1447, "hehehe": 1448, "donggg": 1449, "jt": 1450, "dibayar": 1451, "digital": 1452, "duluan": 1453, "nunggunya": 1454, "kesana": 1455, "diam": 1456, "ono": 1457, "pemberitahuan": 1458, "tindak": 1459, "bgst": 1460, "lho": 1461, "lagih": 1462, "mmber": 1463, "platinum": 1464, "ahh": 1465, "negri": 1466, "apah": 1467, "naik": 1468, "harusnya": 1469, "teliti": 1470, "dinonaktifkan": 1471, "ngelek": 1472, "menggaggu": 1473, "ojek": 1474, "dishope": 1475, "lucu": 1476, "pulau": 1477, "boro": 1478, "kredit": 1479, "terllu": 1480, "padhl": 1481, "trllu": 1482, "tunggakan": 1483, "asik": 1484, "liat2": 1485, "flas": 1486, "bela": 1487, "belain": 1488, "buang": 1489, "20k": 1490, "freeong": 1491, "hari2": 1492, "ini\ud83d\udc4d\ud83d\udc4d\ud83d\udc4d": 1493, "even": 1494, "bisnis": 1495, "shopeex": 1496, "seruu": 1497, "koen": 1498, "makan": 1499, "nungguin": 1500, "mntp": 1501, "pelitt": 1502, "sebel": 1503, "lebay": 1504, "tercantum": 1505, "dapetnya": 1506, "jenis": 1507, "oy": 1508, "kuring": 1509, "postingan": 1510, "ong": 1511, "minim": 1512, "bangkrut": 1513, "difilter": 1514, "hebat": 1515, "mudahh": 1516, "tanda": 1517, "terdeteksi": 1518, "screenshot": 1519, "sangan": 1520, "ska": 1521, "lope": 1522, "bahan": 1523, "peluang": 1524, "trima": 1525, "nilai": 1526, "pinter": 1527, "duduk": 1528, "sekian": 1529, "jp": 1530, "berisik": 1531, "didalamnya": 1532, "tv": 1533, "penyelesaian": 1534, "ae": 1535, "bnr\u00b2": 1536, "expedisinya": 1537, "dipke": 1538, "joget": 1539, "59": 1540, "promosikan": 1541, "minat": 1542, "segi": 1543, "motif": 1544, "tawarkan": 1545, "singkat": 1546, "mandir": 1547, "nya\ud83d\udc4d\ud83d\udc4d\ud83d\udc4d": 1548, "play": 1549, "\u263a\ufe0f\u263a\ufe0f": 1550, "\ud83e\udd1d\ud83d\udc4d\ud83d\udc4d\ud83d\udc4d\ud83d\udc4d\ud83d\udc4d": 1551, "kerena": 1552, "sangatvbagus": 1553, "waduuuh": 1554, "anteng": 1555, "belanjanya": 1556, "samsung": 1557, "a73": 1558, "5g": 1559, "relog": 1560, "masu": 1561, "diinfo": 1562, "lamaaa": 1563, "nyuruh": 1564, "ditokped": 1565, "report": 1566, "dicuekin": 1567, "trouble": 1568, "maksain": 1569, "400": 1570, "ikon": 1571, "kmmpmmkm": 1572, "lk": 1573, "mk": 1574, "koko": 1575, "llml": 1576, "ml": 1577, "lmmlm": 1578, "ke": 1579, "momok": 1580, "nnnomlmlmlm": 1581, "klm": 1582, "\ud83d\udc31\ud83d\udc11\ud83d\udc22\ud83d\udc11\ud83d\udc06\ud83d\udc11\ud83d\udc22\ud83d\udc22\ud83d\udc11\ud83d\udc22\ud83d\udc04\ud83d\udc22\ud83d\udc11\ud83d\udc22\ud83d\udc23\ud83d\udc22\ud83d\udc11\ud83d\udc23\ud83d\udc11\ud83d\udc46\ud83d\udc4c\ud83d\udc46\ud83d\udc11\ud83d\udc11\ud83d\udc11\ud83d\udc11\ud83d\udc11\ud83d\udc11\ud83d\udc04\ud83d\udc37\ud83d\udc11\ud83d\udc11\ud83d\udc11\ud83d\udc11\ud83d\udc11\ud83d\udc11\ud83d\udc11\ud83d\udc11\ud83d\udc11\ud83d\udc0a\ud83d\udc04\ud83d\udc23\ud83d\udc11\ud83d\udc11\ud83d\udc23\ud83d\udc11\ud83d\udc11\ud83d\udc22\ud83d\udc11\ud83d\udc11\ud83d\ude34\ud83d\udc11\ud83d\udc04\ud83d\udc22\ud83d\udc11\ud83d\udc22\ud83d\udc23\ud83d\udc22\ud83d\udc23\ud83d\udc22\ud83d\udc11\ud83d\udc11\ud83d\udc04\ud83d\udc11\ud83d\udc04\ud83d\udc11\ud83d\udc23\ud83d\udc04\ud83d\udc37\ud83d\udc22\ud83d\udc11\ud83d\udc04\ud83d\udc21\ud83d\udc09\ud83c\udf7c\ud83c\udf6d\ud83c\udf5f\ud83d\udc11\ud83d\udc11\ud83d\udc04\ud83d\udc11\ud83d\udc11\ud83d\udc22\ud83d\udc11\ud83d\udc06\ud83c\udf77\ud83c\udf7c\ud83d\udc22\ud83d\udc22\ud83d\udc11\ud83d\udc22\ud83d\udc23\ud83d\udc11\ud83d\udc22\ud83d\udc11\ud83d\udc11\ud83d\udc11\ud83d\udc11\ud83d\udc23\ud83d\udc22\ud83d\udc11\ud83d\udc04\ud83d\udc22\ud83d\udc23\ud83d\udc11\ud83d\udc11\ud83d\udc11\ud83d\udc27\ud83d\udc11\ud83d\udc11\ud83d\udc11": 1583, "\ud83d\udc11\ud83d\udc23\ud83d\udc37\ud83d\udc11\ud83d\udc11\ud83d\udc11\ud83d\udc11\ud83d\udc11\ud83d\udc22\ud83d\udc11\ud83d\udc22\ud83d\udc27\ud83d\udc06\ud83d\udc0a\ud83d\udc1b\ud83c\udf77": 1584, "\ud83d\udc11\ud83d\udc04\ud83d\udc23\ud83d\udc11\ud83d\udc22\ud83d\udc04\ud83d\udc23\ud83d\udc23\ud83d\udc04\ud83d\udc11\ud83d\udc11\ud83d\udc22\ud83d\udc11\ud83d\udc06\ud83d\udc0a\ud83d\udc11\ud83d\udc04\ud83d\udc37": 1585, "onwernya": 1586, "melimpah": 1587, "rejekinya": 1588, "berbagi": 1589, "sesema": 1590, "manusia": 1591, "percuma": 1592, "jka": 1593, "laku": 1594, "kelap": 1595, "kelip": 1596, "warna": 1597, "akjn": 1598, "selelu": 1599, "hadiahnya": 1600, "cocoklah": 1601, "mensupport": 1602, "merespone": 1603, "crew": 1604, "qualitas": 1605, "product": 1606, "rata2": 1607, "murahan": 1608, "dipertahankan": 1609, "penjelasan": 1610, "description": 1611, "uraian": 1612, "performance": 1613, "nys": 1614, "ditingkatkan": 1615, "compotiter": 1616, "ketimbang": 1617, "benarnya": 1618, "2rb": 1619, "weee": 1620, "ampe": 1621, "40rb": 1622, "keatas": 1623, "shoop2": 1624, "diminta": 1625, "salaaaaaah": 1626, "saalah": 1627, "ciptaan": 1628, "huftt": 1629, "chace": 1630, "abad": 1631, "gercep": 1632, "dimenangi": 1633, "2buln": 1634, "displaynya": 1635, "ngampassss": 1636, "rajin": 1637, "kakak": 1638, "biarkan": 1639, "ceoat": 1640, "pernah": 1641, "gabut": 1642, "support": 1643, "qqa": 1644, "watu": 1645, "wengi": 1646, "dabest": 1647, "\ud83d\udc4f\ud83d\ude4c\ud83d\uddff": 1648, "spyjam": 1649, "pemberitauan": 1650, "undur": 1651, "nentoood": 1652, "nda": 1653, "\ud83d\udc36": 1654, "ap": 1655, "aktivasi": 1656, "didik": 1657, "ajar": 1658, "santun": 1659, "pafa": 1660, "songong": 1661, "ngutamg": 1662, "gwehj": 1663, "bilek": 1664, "donlot": 1665, "teramat": 1666, "fek": 1667, "tombol": 1668, "dislaik": 1669, "awikwok": 1670, "cuy\ud83d\ude05\u261d\ufe0foe": 1671, "olang": 1672, "loo": 1673, "bubarkan": 1674, "az": 1675, "banding": 1676, "memudah": 1677, "ygvmau": 1678, "menangin": 1679, "25k": 1680, "dibawahnya": 1681, "yaudah": 1682, "norak": 1683, "serasa": 1684, "cuma2": 1685, "vhoucerny": 1686, "lemotnya": 1687, "anti": 1688, "pelayananya": 1689, "aplikasi\ud83d\udc4d": 1690, "kembangin": 1691, "btw": 1692, "pembuat": 1693, "daktar": 1694, "setia": 1695, "ngantar": 1696, "alhamdulillaah": 1697, "bersusah": 1698, "dibantu": 1699, "menghadapi": 1700, "ramah\ud83d\udc4d": 1701, "\u2b50\u2b50\u2b50\u2b50\u2b50\u2b50\u2b50\u2b50\u2b50\u2b50\u2b50\u2b50": 1702, "ongkirnyaaaa": 1703, "bangeeeettttttt": 1704, "\u256c": 1705, "\u00f2": 1706, "\u2038": 1707, "\u00f3": 1708, "\ud83d\udc4d\ud83c\udffe": 1709, "gembel": 1710, "lamabat": 1711, "boleh": 1712, "terbuka": 1713, "lebar": 1714, "minimnya": 1715, "\ud83e\udd2d": 1716, "playlater": 1717, "low": 1718, "bro": 1719, "okokokoko": 1720, "masalah": 1721, "dirimunya": 1722, "bos\ud83d\ude01\ud83e\udd2d": 1723, "janga": 1724, "komen": 1725, "diliat": 1726, "ksopanan": 1727, "sopy": 1728, "synx": 1729, "tmn": 1730, "sirver": 1731, "br": 1732, "lngsng": 1733, "limit\ud83d\ude14\ud83d\ude14entah": 1734, "\ud83d\ude14\ud83d\ude14": 1735, "satuin": 1736, "animasi": 1737, "judi": 1738, "rame": 1739, "paylatter": 1740, "ilove": 1741, "yaaaa": 1742, "sandi": 1743, "trlepon": 1744, "kartunya": 1745, "saldonya": 1746, "pencerahannya": 1747, "gmail": 1748, "balanja": 1749, "worth": 1750, "2024": 1751, "ngebawa": 1752, "newjeans": 1753, "indonesia\ud83c\udf1e": 1754, "ditempat": 1755, "sbelum": 1756, "bngttt\ud83d\ude2d": 1757, "muda": 1758, "mbanking": 1759, "penyalah": 1760, "gunaan": 1761, "barangny": 1762, "menjengkelkan": 1763, "berkali2": 1764, "kbijakannya": 1765, "pula": 1766, "ads": 1767, "\u2b50xxxx": 1768, "air": 1769, "xd": 1770, "\ud83d\udc4c\ud83d\udc4c\ud83d\udc4c": 1771, "ngeleng": 1772, "sesad": 1773, "nyo": 1774, "pesananya": 1775, "tambahkan": 1776, "\ud83d\ude10": 1777, "dirugikan": 1778, "comeback": 1779, "memperbaiki": 1780, "makin2": 1781, "yeeee": 1782, "sumber": 1783, "sultan": 1784, "dongg": 1785, "sore": 1786, "lohhh": 1787, "\ud83d\udc4e\ud83c\udffb\ud83d\udc4e\ud83c\udffb": 1788, "youtube": 1789, "lamah": 1790, "pertama": 1791, "diselesaikan": 1792, "tercentang": 1793, "ktl": 1794, "keree\u00e8en": 1795, "shopeelayter": 1796, "makai": 1797, "menyebabkan": 1798, "affiliatesnya": 1799, "illa": 1800, "mengarah": 1801, "18": 1802, "iklan\u00b2": 1803, "dihilangkan": 1804, "jadikan": 1805, "uptade": 1806, "maless": 1807, "sumpahhh": 1808, "3hri": 1809, "blurr": 1810, "ksih": 1811, "repon": 1812, "koreksi": 1813, "kirm": 1814, "komunikasi": 1815, "smpnya": 1816, "anjg": 1817, "tinggi": 1818, "seruuu": 1819, "terbaikkk": 1820, "pesat": 1821, "meningkat": 1822, "perhatian": 1823, "mehong": 1824, "\ud83e\udd22": 1825, "pending2": 1826, "mendesak": 1827, "sepele": 1828, "nihilll": 1829, "pelanggaran": 1830, "eeq": 1831, "gabisa2": 1832, "lebi": 1833, "diandalkan": 1834, "penguras": 1835, "\ud83d\udcb8\ud83d\udcb8\ud83d\udcb8\ud83d\udcb8\ud83d\udcb8": 1836, "kirimin": 1837, "dipersingkat": 1838, "ditentukan": 1839, "calon": 1840, "nyaranin": 1841, "pikun": 1842, "amezing": 1843, "tepat": 1844, "ember": 1845, "ny\u2764\ufe0f": 1846, "muncu": 1847, "ngetik": 1848, "pi": 1849, "sopipi": 1850, "okeyy": 1851, "pembayaranya": 1852, "mantuul": 1853, "kamu": 1854, "shopii": 1855, "nonaktifkan": 1856, "shoopi": 1857, "jutaan": 1858, "puluhan": 1859, "merespon": 1860, "shopengak": 1861, "skr": 1862, "\u2764\ufe0f": 1863, "\ud83e\udd70\ud83e\udd70\ud83e\udd70\ud83e\udd70": 1864, "tranfer": 1865, "atau": 1866, "dipesan\ud83d\ude0a": 1867, "muter": 1868, "gas": 1869, "\ud83d\ude01\ud83d\ude01": 1870, "tq": 1871, "jwb": 1872, "semena2": 1873, "nasabah": 1874, "menyanggupi": 1875, "menindak": 1876, "jk": 1877, "sop": 1878, "sosis": 1879, "ngayel": 1880, "tiada": 1881, "duanya": 1882, "senonoh": 1883, "pertonton": 1884, "sanyang": 1885, "oleh": 1886, "vido": 1887, "lmyan": 1888, "ordern": 1889, "shopee\ud83d\ude0a": 1890, "sadis": 1891, "rebu": 1892, "oengiriman": 1893, "nawarin": 1894, "menghambat": 1895, "bacaan": 1896, "lagi\ud83d\udc4e\ud83d\udc4e\ud83d\udc4e\ud83d\udc4e\ud83d\udc4e\ud83d\udc4e\ud83d\udc4e\ud83d\udc4e\ud83d\udc4e\ud83d\udc4e\ud83d\udc4e\ud83d\udc4e": 1897, "luck": 1898, "produk2nya": 1899, "dibutuhkan": 1900, "dicari": 1901, "disc": 1902, "\ud83c\udf82": 1903, "internetnya": 1904, "birhday": 1905, "recomded": 1906, "pemula": 1907, "telusuri": 1908, "tempatnya": 1909, "murah\ud83d\ude2d\ud83d\ude4f\ud83d\ude4f": 1910, "lain\u00b2": 1911, "grtis": 1912, "kenapaaa": 1913, "shopee\ud83d\udc4d\ud83d\udc4d\ud83d\udc4d\ud83d\udc4d": 1914, "begettt": 1915, "membuahkan": 1916, "\ud83d\udc4c\ud83d\udc4c\ud83d\udc4c\ud83d\udc4d\ud83d\udc4d\ud83d\udc4d\u2665\ufe0f\u2665\ufe0f\u2665\ufe0f": 1917, "lumayang": 1918, "boogaan": 1919, "teryata": 1920, "terburuk": 1921, "maruk": 1922, "najis": 1923, "boncos": 1924, "mavisnv": 1925, "jelekkkkkkkk": 1926, "mangpaat": 1927, "sebeell": 1928, "saat": 1929, "huh": 1930, "gaada": 1931, "\ud83d\ude22": 1932, "jawabannya": 1933, "denpasar": 1934, "karuan": 1935, "sedangkn": 1936, "miom3": 1937, "kabupaten": 1938, "kampung": 1939, "kalou": 1940, "atou": 1941, "jps": 1942, "mantabz": 1943, "pln": 1944, "terlanjur": 1945, "mengendapkan": 1946, "ngakak": 1947, "ngereat": 1948, "anjir": 1949, "xsprees": 1950, "sejam": 1951, "gabungan": 1952, "gada": 1953, "niatan": 1954, "memangnya": 1955, "senggaknya": 1956, "drivernya": 1957, "dibiarin": 1958, "astaga": 1959, "lahhh\ud83e\udd0f\ud83d\udc4c": 1960, "rapi": 1961, "\u00b2": 1962, "pusink": 1963, "ilan": 1964, "siiip": 1965, "nagih": 1966, "sd": 1967, "sentosa": 1968, "sebagamana": 1969, "mestinya": 1970, "\ud83e\udd73\ud83e\udd73": 1971, "recomen": 1972, "cc": 1973, "ktp": 1974, "kepakai": 1975, "revisi": 1976, "kesekian": 1977, "kalinya": 1978, "bangettttt": 1979, "ajaaa": 1980, "susahnya": 1981, "napa": 1982, "teruslah": 1983, "lancaar": 1984, "shopee\ud83d\ude0d": 1985, "fair": 1986, "okta": 1987, "velg0": 1988, "mssd": 1989, "ciee": 1990, "8f3": 1991, "azzek3chuckemang": 1992, "diubah": 1993, "vs": 1994, "ososok": 1995, "cd": 1996, "wr": 1997, "eddy": 1998, "exercise": 1999, "kx": 2000, "xsoax3l": 2001, "exo": 2002, "obvitkoc": 2003, "llokkl": 2004, "wkwko": 2005, "\ud83c\udd91a": 2006, "'dari": 2007, "pipi": 2008, "lock": 2009, "cawa": 2010, "es": 2011, "eddykoc": 2012, "ak": 2013, "diisi": 2014, "xi": 2015, "xsyg": 2016, "us": 2017, "sosok": 2018, "sonsemngt\ud83d\udc98\ud83e\udd10dllsemngt": 2019, "izzah": 2020, "ekm": 2021, "omongan": 2022, "skra": 2023, "arahin": 2024, "bagua": 2025, "blokirrr": 2026, "60": 2027, "laen": 2028, "kualitasnya": 2029, "captionnya": 2030, "dicek": 2031, "knt0l": 2032, "bukk": 2033, "retry": 2034, "moba": 2035, "skalian": 2036, "ping": 2037, "5vs5": 2038, "pecahkan": 2039, "kepala": 2040, "land": 2041, "down": 2042, "kntol": 2043, "pepk": 2044, "bosen": 2045, "liatnya": 2046, "cabang": 2047, "cikande": 2048, "deket": 2049, "tmpat": 2050, "gog": 2051, "se'pengalaman": 2052, "memang": 2053, "adanya": 2054, "satunya": 2055, "dikirm": 2056, "tmpt": 2057, "tsb": 2058, "smpenya": 2059, "walaupun": 2060, "padahalsaya": 2061, "psn": 2062, "hari\u00b2": 2063, "selidiki": 2064, "lanjut": 2065, "tampa": 2066, "tetapi": 2067, "aplikasinnya": 2068, "contoh": 2069, "11": 2070, "waktunya": 2071, "tenanggg": 2072, "rangking": 2073, "kok\ud83e\udd73\ud83e\udd73\ud83e\udd73\ud83e\udd70\ud83e\udd70": 2074, "aga": 2075, "deluan": 2076, "ketinggalan": 2077, "kalia": 2078, "ball": 2079, "pool": 2080, "gg": 2081, "dimurahin": 2082, "mantaps": 2083, "lenyap": 2084, "diperbaikin": 2085, "masal": 2086, "titik": 2087, "drop": 2088, "logistik": 2089, "wilayah": 2090, "cirinten": 2091, "kab": 2092, "lebak": 2093, "banten": 2094, "secepat": 2095, "kilat": 2096, "dibanding": 2097, "platform": 2098, "pesannan": 2099, "cahce": 2100, "1000x": 2101, "besok": 2102, "ongkir\ud83d\ude01": 2103, "pokoe": 2104, "mantapsssss": 2105, "lemotttt": 2106, "ekppektasi": 2107, "past": 2108, "respons": 2109, "donwload": 2110, "orngkirnya": 2111, "olshop": 2112, "favourite": 2113, "profesional": 2114, "dahulu": 2115, "resolusi": 2116, "nnton": 2117, "boros": 2118, "infokan": 2119, "topp": 2120, "\ud83d\udc4c": 2121, "\u53d1\u7684\u5230\u516c\u53f8\u53bb": 2122, "keren\ud83e\udd70\ud83e\udd70\ud83e\udd70\ud83e\udd70": 2123, "bgetttt": 2124, "sekaliiii": 2125, "syukaa": 2126, "anjirr": 2127, "bguss": 2128, "hot": 2129, "hadeeh": 2130, "ujung": 2131, "shedihh": 2132, "\ud83d\ude29": 2133, "nabung": 2134, "ehh": 2135, "bulannya": 2136, "bodong": 2137, "akunnya": 2138, "malu": 2139, "jaringannya": 2140, "banget\ud83d\ude2dpadahal": 2141, "yt": 2142, "ngegame": 2143, "banget\ud83d\ude2dudah": 2144, "terikini": 2145, "pemakaiannya": 2146, "refund": 2147, "telp": 2148, "muka": 2149, "malahh": 2150, "standard": 2151, "gooooood": 2152, "hihihi": 2153, "clik": 2154, "vertifikasi": 2155, "freeongkir": 2156, "terbaiklah": 2157, "alay": 2158, "rendah": 2159, "ude": 2160, "krng": 2161, "ijo": 2162, "bda": 2163, "ngotak\ud83e\udd2d": 2164, "25": 2165, "27": 2166, "useless": 2167, "nyampek": 2168, "kekita": 2169, "uang2": 2170, "enggk": 2171, "sampek": 2172, "hongkong": 2173, "bawak": 2174, "merchen": 2175, "berguna\ud83d\udc4d": 2176, "burukk": 2177, "burukkkkkkkk": 2178, "bnerin": 2179, "kouta": 2180, "sopipipipipiiiiii": 2181, "thankyouuu": 2182, "sarana": 2183, "selektif": 2184, "satu": 2185, "ttep": 2186, "dengar": 2187, "mencoba": 2188, "menginstal": 2189, "keprnkat": 2190, "disaring": 2191, "mengandung": 2192, "pornografi": 2193, "membangun": 2194, "2018": 2195, "tingkahnya": 2196, "gilak": 2197, "tooop": 2198, "tanibae": 2199, "dsh": 2200, "ejecejcek": 2201, "membantu\ud83e\udef0\ud83e\udef0": 2202, "shooping": 2203, "pokokknya": 2204, "baik\u00b2": 2205, "redy": 2206, "enggakk": 2207, "biasanya": 2208, "ngecht": 2209, "dluan": 2210, "dluann": 2211, "bngt\ud83d\ude42dn": 2212, "pemgiriman": 2213, "ban": 2214, "anter": 2215, "tampat": 2216, "pelayanam": 2217, "kredi": 2218, "shoopeepay": 2219, "999": 2220, "tolonga": 2221, "gercepin": 2222, "keep": 2223, "fine": 2224, "work": 2225, "guys": 2226, "cihuyyy": 2227, "harapan": 2228, "reselernya": 2229, "thr": 2230, "beeesttt": 2231, "\ud83d\udc4f\ud83d\udc4f\ud83d\udc4f\ud83d\udc4f\ud83d\udc4f\ud83d\udc4f\ud83d\udc4f\ud83d\udc4f\ud83d\udc4f": 2232, "patut": 2233, "dikasi": 2234, "penghargaan": 2235, "\ud83d\udc90": 2236, "astimasi": 2237, "serah": 2238, "kelama": 2239, "qn": 2240, "mengklaim": 2241, "helpfull": 2242, "people": 2243, "siiiip": 2244, "bagus\ud83d\udc4d\ud83c\udffc\ud83d\udc4d\ud83c\udffc\ud83d\udc4d\ud83c\udffc\ud83d\udc4d\ud83c\udffc": 2245, "ngantri": 2246, "sekarang\ud83d\ude4f": 2247, "tuntut": 2248, "jaskir": 2249, "bngtttt": 2250, "dateng2": 2251, "keselll": 2252, "shopee\ud83d\udc4e\ud83d\udc4e\ud83d\ude21\ud83d\ude21\ud83d\udd25\ud83d\udd25": 2253, "laternya": 2254, "terimakasih\ud83d\ude4f": 2255, "perjalan": 2256, "joss": 2257, "\ud83d\udc4d\ud83d\udc4d\ud83d\udc4d\ud83d\udc4d\ud83d\udc4d\ud83d\udc4d\ud83d\udc4d": 2258, "nipu2": 2259, "brantas": 2260, "afiliasi": 2261, "samgat": 2262, "barang\u00b2nya": 2263, "4ribu": 2264, "zuara": 2265, "yagesya": 2266, "padahal\ud83d\udc49syudah": 2267, "terbarrrrrru": 2268, "amanhl": 2269, "huhuhu": 2270, "pembayarannya": 2271, "total": 2272, "sope": 2273, "hrganya": 2274, "maksud": 2275, "mikir": 2276, "nya\ud83d\udc4d\ud83d\udc4d\ud83d\udc4f": 2277, "cma": 2278, "kerjasama": 2279, "dengan": 2280, "cepatt": 2281, "kasihh": 2282, "ttg": 2283, "mikirin": 2284, "xpedisi": 2285, "hargai": 2286, "sgla": 2287, "sswtu": 2288, "wlpun": 2289, "debu": 2290, "insyallah": 2291, "pantau": 2292, "26": 2293, "hape": 2294, "nokia": 2295, "senter": 2296, "minta": 2297, "asuransi": 2298, "kerusakan": 2299, "tangan": 2300, "foodnya": 2301, "munculll": 2302, "pembaharuan": 2303, "muncull": 2304, "payahhh": 2305, "riau": 2306, "inhil": 2307, "kateman": 2308, "ambilnya": 2309, "permudah": 2310, "benget": 2311, "kata\ud83d\ude29\ud83d\ude29\ud83d\ude29\ud83d\ude29": 2312, "tahunan": 2313, "bisa2nya": 2314, "diteror": 2315, "3jutaan": 2316, "diuber": 2317, "kaha": 2318, "ginj": 2319, "lunasin": 2320, "sosuli": 2321, "meringankan": 2322, "tenaga": 2323, "satttttt": 2324, "lancar2": 2325, "idolaku": 2326, "lacak": 2327, "\ud83d\udc4d\ud83d\udcaf": 2328, "bagus\u2079": 2329, "ajasi": 2330, "\ud83d\ude12\ud83d\ude44\ud83d\ude12": 2331, "sih\ud83d\uddff": 2332, "jangan": 2333, "nolak": 2334, "ora": 2335, "gratisan": 2336, "manta": 2337, "menggangggu": 2338, "muncul2": 2339, "menggangguuuuuuuuuuuuuu": 2340, "persetujuan": 2341, "onlien": 2342, "tempat": 2343, "ok\ud83d\udc4d": 2344, "inibagus": 2345, "nunjukin": 2346, "taruh": 2347, "nemu": 2348, "ongkirrr": 2349, "anjayy": 2350, "aplg": 2351, "asing": 2352, "memeberikan": 2353, "training": 2354, "berkwalitas": 2355, "berkelas": 2356, "kpd": 2357, "mantaf": 2358, "peningkatan": 2359, "menejemen": 2360, "cobain": 2361, "auliya": 2362, "dibenerin": 2363, "1x24": 2364, "ngaruh": 2365, "keluarin": 2366, "10ribu": 2367, "lagiii": 2368, "katanya": 2369, "modus": 2370, "inimah": 2371, "area": 2372, "menepati": 2373, "setiiap": 2374, "indonesi": 2375, "lambattt": 2376, "bot": 2377, "choki": 2378, "oh": 2379, "ce\ud83d\ude05\ud83e\udd26\ud83c\udffd\u200d\u2642\ufe0f": 2380, "\ud83d\ude05\ud83d\ude03\ud83d\ude01": 2381, "dii": 2382, "perbaharui": 2383, "jadii": 2384, "susak": 2385, "troli": 2386, "bhgygy": 2387, "nne": 2388, "ju": 2389, "yyr": 2390, "2bjjiu": 2391, "sagat": 2392, "nie": 2393, "jet": 2394, "mingggu": 2395, "yaang": 2396, "langanan": 2397, "tangerang": 2398, "kamis": 2399, "spxnya": 2400, "kacau": 2401, "haduuh": 2402, "be": 2403, "\u2078": 2404, "88": 2405, "its": 2406, "membenarkan": 2407, "bagat": 2408, "orang2": 2409, "sibuk": 2410, "filternya": 2411, "perfek": 2412, "ol": 2413, "cintailah": 2414, "\ud83d\ude01\ud83d\udc4d\ud83d\udc4d\ud83d\udc4d": 2415, "sng": 2416, "mrai": 2417, "elek": 2418, "wk": 2419, "kcw": 2420, "tnn": 2421, "sorry": 2422, "tk": 2423, "hps": 2424, "\ud83d\udc9c\ud83d\udc9c\ud83d\udc9c": 2425, "inisi": 2426, "\ud83c\udf1f": 2427, "dunia": 2428, "binggun": 2429, "seabnk": 2430, "pdahl": 2431, "colab": 2432, "idoll": 2433, "berlanja": 2434, "rakus": 2435, "overload": 2436, "mkanya": 2437, "nganter": 2438, "istirahat": 2439, "klian": 2440, "bola": 2441, "bali": 2442, "pembelanjaan": 2443, "awokawok": 2444, "aka": 2445, "terkoneksi": 2446, "sweat": 2447, "sebatas": 2448, "sanggar": 2449, "bossq": 2450, "virus": 2451, "tksh": 2452, "naisek": 2453, "tingkatakan": 2454, "segitu": 2455, "recomendet": 2456, "gudddd": 2457, "racun": 2458, "bahayaaa": 2459, "barangya": 2460, "bajakan": 2461, "dirubah": 2462, "sepengetahuan": 2463, "seting": 2464, "sukak": 2465, "dehhhch": 2466, "dsb": 2467, "pilih2": 2468, "berhak": 2469, "keberuntungan": 2470, "kesukses": 2471, "pokonamah": 2472, "68": 2473, "sampai\u00b2": 2474, "kulir": 2475, "shopee\ud83e\udd70\ud83e\udd17\ud83e\udd70": 2476, "dilapangan": 2477, "bubar": 2478, "wahhh": 2479, "yo": 2480, "sayangnya": 2481, "pengemasan": 2482, "sangaaaaat": 2483, "gunain": 2484, "bah": 2485, "ngedownload": 2486, "coek": 2487, "naro": 2488, "tulis": 2489, "erorr": 2490, "hmmm": 2491, "pngaturan": 2492, "sofy": 2493, "amiiin": 2494, "kodenya": 2495, "dibayarkan": 2496, "ditindaklanjutin": 2497, "mantull": 2498, "betulll\ud83d\udc4d\ud83d\udc4d\ud83d\udc4d\ud83d\ude0e\ud83d\udc4d\ud83d\udc4d\ud83d\udc4d\ud83d\ude0e\ud83d\udc4d\ud83d\udc4d\ud83d\ude0e": 2499, "okai": 2500, "diminimalisir": 2501, "te": 2502, "aipon": 2503, "bestlah": 2504, "pokoknya\ud83d\udc4d\ud83d\udc4d\ud83d\udc4d\ud83d\udc4d\ud83d\udc4d": 2505, "terys": 2506, "tiktokshoop": 2507, "berentiny": 2508, "mall": 2509, "keren\ud83d\udc4d\ud83d\udc4d": 2510, "shoope\ud83d\udc4d\ud83d\udc4d\ud83d\udc4d\ud83d\udc4d\ud83d\udc4d": 2511, "10ribuuu": 2512, "yu": 2513, "paan": 2514, "nyampenya": 2515, "jangkau": 2516, "usahak": 2517, "krim": 2518, "cobanya": 2519, "bantuannya": 2520, "belanjq": 2521, "\ud83d\udc4d\ud83d\udc4d\ud83d\udc4d\ud83d\udc4d\ud83d\udc4d\ud83d\ude4f\ud83d\ude4f\ud83d\ude4f\ud83d\ude4f\ud83d\ude4f": 2522, "ppppp": 2523, "itumz": 2524, "\ud83d\udc4d\ud83d\udc4c\ud83e\udd1d": 2525, "\ud83e\udd32\ud83e\udd32\ud83e\udd32": 2526, "supreme": 2527, "mentolo": 2528, "hapos": 2529, "pencarian": 2530, "progres": 2531, "menyiram": 2532, "tanaman": 2533, "berharga": 2534, "\ud83d\ude24\ud83d\ude20\ud83e\udd2c": 2535, "msk\u00b2": 2536, "kpn": 2537, "duitnya": 2538, "onkirnya": 2539, "pertahan": 2540, "diapa": 2541, "apain": 2542, "\u2639\ufe0f\u2639\ufe0f": 2543, "perifikasi": 2544, "web": 2545, "sblah": 2546, "satt": 2547, "mudahkan": 2548, "ngatur": 2549, "setan": 2550, "ngehapus": 2551, "karana": 2552, "tedateksi": 2553, "akunya": 2554, "luarbiass": 2555, "gandos": 2556, "rere": 2557, "gocing": 2558, "lemooottt": 2559, "bgtu": 2560, "menbuat": 2561, "dong\ud83e\udec2": 2562, "dendanya": 2563, "bsgus": 2564, "mksh": 2565, "hapus\ud83d\udc4d\ud83d\udc4d\ud83d\udc4d\ud83d\ude4f\ud83d\ude4f\ud83d\ude4f\u2b50\u2b50\u2b50\u2b50\u2b50": 2566, "unduh": 2567, "mngclaim": 2568, "hdiah": 2569, "mengangu": 2570, "original": 2571, "balesan": 2572, "nyambung": 2573, "peralatannya": 2574, "expetasi": 2575, "layanin": 2576, "android": 2577, "speak": 2578, "mumpuni": 2579, "baget": 2580, "agen\u00b2": 2581, "spylater": 2582, "dibelikan": 2583, "beras": 2584, "minyak": 2585, "sayur": 2586, "bawang": 2587, "\ud83d\udc4d\ud83d\udcaf\ud83d\udc4f\ud83d\udc4f": 2588, "pag": 2589, "kepakek": 2590, "\ud83d\ude11": 2591, "data2": 2592, "kenpa": 2593, "bantuanya": 2594, "kak\ud83d\ude4f": 2595, "\ud83d\ude4f\ud83d\ude4f\ud83d\ude4f\ud83d\ude4f\ud83d\ude2d\ud83d\ude2d\ud83d\ude2d\ud83d\ude2d\ud83d\ude2d": 2596, "rpx": 2597, "gax": 2598, "becus": 2599, "\ud83d\ude09\ud83d\udc4d": 2600, "nya\u263a\u263a\u263a\u263a": 2601, "yuuuk": 2602, "identik": 2603, "paska": 2604, "reply": 2605, "kotol": 2606, "bak": 2607, "pecah": 2608, "pwler": 2609, "benerrr": 2610, "take": 2611, "uzzz": 2612, "ikutin": 2613, "miminnya": 2614, "min\ud83d\ude01\ud83d\ude01": 2615, "pedia": 2616, "spesipikasi": 2617, "muter2": 2618, "spiker": 2619, "sabun": 2620, "cuci": 2621, "penjual2": 2622, "tampilkn": 2623, "daganga": 2624, "mereka": 2625, "paken": 2626, "ase": 2627, "sudh": 2628, "gudang": 2629, "sngat": 2630, "banget\ud83e\udd70\ud83d\ude0d\ud83d\ude18": 2631, "\ud83d\udc4c\ud83d\udc4c": 2632, "bagosss": 2633, "bbelanja": 2634, "atw": 2635, "pinjm": 2636, "nya\ud83d\udc4d": 2637, "salammp": 2638, "produk''": 2639, "modifikasi": 2640, "adaa": 2641, "kereen": 2642, "shoopee\ud83d\ude0d\ud83d\ude0d\ud83d\udc4d\ud83d\udc4d\u2764\ufe0f\u2764\ufe0f\u2764\ufe0f\u2764\ufe0f\u2764\ufe0f": 2643, "mks": 2644, "ribed": 2645, "adm": 2646, "dihubungi": 2647, "2jt": 2648, "gps": 2649, "hanyak": 2650, "unik": 2651, "tercoret": 2652, "discone": 2653, "tik": 2654, "hrg": 2655, "rubah": 2656, "mbak": 2657, "shopee\ud83d\udc4d\ud83d\udc4d\ud83d\udc4d": 2658, "woww": 2659, "masuk\u00b2": 2660, "24": 2661, "balik\u00b2": 2662, "kecolongan": 2663, "90": 2664, "haru": 2665, "komen2": 2666, "bu": 2667, "iss": 2668, "membatalkan": 2669, "rabb": 2670, "allahumma": 2671, "betul": 2672, "item": 2673, "besaran": 2674, "nasib": 2675, "berhasil": 2676, "dikirimkan": 2677, "penjadwalan": 2678, "saller": 2679, "all": 2680, "bersaing": 2681, "rabbal": 2682, "alamin": 2683, "kesulitan": 2684, "seiring": 2685, "berjlnnya": 2686, "dibalik": 2687, "baguss\ud83d\udc4d\ud83d\udc4d\ud83d\udc4d": 2688, "hadeh": 2689, "memuas": 2690, "set": 2691, "garansi": 2692, "beginihvenak": 2693, "pesrn": 2694, "sendri": 2695, "mantullll": 2696, "maren": 2697, "rekomen": 2698, "teruntuk": 2699, "pesaing": 2700, "dapetin": 2701, "jujur": 2702, "beralih": 2703, "onlie": 2704, "ingat": 2705, "pintar": 2706, "ponsel": 2707, "dipilihnya": 2708, "mo02": 2709, "do02": 2710, "mengatasinya": 2711, "incar": 2712, "sebelumnya": 2713, "seneng": 2714, "papa": 2715, "sk": 2716, "klalau": 2717, "stoknya": 2718, "stok": 2719, "jink": 2720, "kelancaran": 2721, "shopyy": 2722, "mantabbbbb": 2723, "ugly": 2724, "gilaan": 2725, "manteppppppp": 2726, "berkibar": 2727, "konsekwen": 2728, "pelayan": 2729, "apaan": 2730, "pantengin": 2731, "detik": 2732, "incaran": 2733, "habiiiisss": 2734, "ngebelain": 2735, "brngnya": 2736, "slah": 2737, "diskripsi": 2738, "untungin": 2739, "pertahankn": 2740, "handpone": 2741, "dilaptop": 2742, "diweb": 2743, "verifiaksi": 2744, "dihandpone": 2745, "balasan": 2746, "softcase": 2747, "jelek2": 2748, "pengecekan": 2749, "onkir": 2750, "dikurangi\ud83d\ude4f": 2751, "reset": 2752, "barcode": 2753, "kekeh": 2754, "pedagangnya": 2755, "ekonomi": 2756, "\ud83d\ude12\ud83d\ude11": 2757, "nalar": 2758, "iming2": 2759, "mmberikan": 2760, "fositiv": 2761, "memancing": 2762, "dikirimkn": 2763, "gtu": 2764, "\ud83d\ude20": 2765, "muak": 2766, "taro": 2767, "seblum": 2768, "unfol": 2769, "dowlod": 2770, "rxpres": 2771, "sepadan": 2772, "wiwin7": 2773, "sc": 2774, "hzyc": 2775, "eb": 2776, "dtang": 2777, "istimewa": 2778, "afiliator": 2779, "pikirin": 2780, "ngeluarin": 2781, "pengaturan": 2782, "tingkah": 2783, "ngikutin": 2784, "memenangkan": 2785, "laancar": 2786, "pengemas": 2787, "koolk": 2788, "koolooo": 2789, "pertasi": 2790, "ucapkan": 2791, "kata2": 2792, "trims": 2793, "gratisin": 2794, "yh": 2795, "perbaiki\ud83d\ude42": 2796, "biyar": 2797, "rekom": 2798, "trsebut": 2799, "cepatttt": 2800, "jaga": 2801, "device": 2802, "snapdragon": 2803, "gen": 2804, "motor": 2805, "standby": 2806, "bohongi": 2807, "munculah": 2808, "wkwkwkwkwk": 2809, "pengin": 2810, "swwww": 2811, "fddudg": 2812, "kursi": 2813, "simulator": 2814, "sklii": 2815, "shopingnya": 2816, "jobs": 2817, "bg": 2818, "gede\u2639\ufe0f": 2819, "dwehhhhh": 2820, "brengsek": 2821, "pesenannya": 2822, "diskonya": 2823, "makasi": 2824, "ongkirnyaaa": 2825, "menanggapi": 2826, "diserahkan": 2827, "ituuu": 2828, "bolak": 2829, "balik": 2830, "pnah": 2831, "sbg": 2832, "beol": 2833, "too": 2834, "never": 2835, "disappoints": 2836, "kelock": 2837, "eitt": 2838, "tg": 2839, "mao": 2840, "semen": 2841, "hebel": 2842, "baja": 2843, "daaaaaahhh": 2844, "gangguuuuuuu": 2845, "always": 2846, "used": 2847, "this": 2848, "for": 2849, "apalah": 2850, "m02": 2851, "memaafkan": 2852, "membatu": 2853, "gan": 2854, "padahl": 2855, "kuat": 2856, "seruuuuu": 2857, "kehilangan": 2858, "dopee": 2859, "gapapa": 2860, "dia": 2861, "mageran": 2862, "dpaket": 2863, "optimal": 2864, "ekspess": 2865, "jemput2": 2866, "sekarang2": 2867, "searching": 2868, "spek": 2869, "kentang": 2870, "dihapusin": 2871, "org2": 2872, "nontonin": 2873, "penggunaanya": 2874, "padamu": 2875, "bgusass": 2876, "aplikansinya": 2877, "optimize": 2878, "jalanin": 2879, "lolos": 2880, "pengajuan\ud83d\ude44": 2881, "gesss": 2882, "bett": 2883, "nii": 2884, "apkkkkk": 2885, "motong": 2886, "jelass": 2887, "alhamdulilhah": 2888, "ma": 2889, "amannah": 2890, "wuhabahahah": 2891, "kecewakan": 2892, "lis": 2893, "kaca": 2894, "inova": 2895, "pariasi": 2896, "krum": 2897, "wiper": 2898, "tetangga\ud83d\ude4f\ud83d\ude4f": 2899, "dng": 2900, "ratakan": 2901, "nya\ud83d\ude0c\ud83d\ude4f\ud83d\ude4f": 2902, "kucing2an": 2903, "dibatalin": 2904, "logo2": 2905, "variasi": 2906, "modern": 2907, "muncul\u00b2": 2908, "trosss": 2909, "ome": 2910, "wkwkwk": 2911, "tidur": 2912, "bertahun": 2913, "diberesin": 2914, "diem": 2915, "hank": 2916, "hapenya": 2917, "secrool": 2918, "tnp": 2919, "tolomg": 2920, "systemnya": 2921, "jik": 2922, "cr": 2923, "bln": 2924, "dkt": 2925, "lgsg": 2926, "larisnya": 2927, "perform": 2928, "wining": 2929, "matiin": 2930, "bagusin": 2931, "kabarin": 2932, "complain": 2933, "digubris": 2934, "kelarnya": 2935, "terutama": 2936, "masukin": 2937, "lucunya": 2938, "pos": 2939, "helpful": 2940, "\ud83d\udc4d\ud83c\udffd": 2941, "birtday": 2942, "ketepatan": 2943, "\ud83d\udc4d\ud83c\udffb\ud83d\udc4d\ud83c\udffb\ud83e\udd1d\ud83d\ude4f\ud83c\udffc": 2944, "agk": 2945, "penyimpanan": 2946, "ngebuat": 2947, "paketan": 2948, "kdng": 2949, "obat": 2950, "pembesar": 2951, "pd": 2952, "lingerie": 2953, "pantas": 2954, "sprti": 2955, "kalangan": 2956, "urusan": 2957, "load": 2958, "pertombangkan": 2959, "walu": 2960, "vidionya": 2961, "kelantan": 2962, "dls": 2963, "terbukti": 2964, "pitur": 2965, "kont": 2966, "ngent": 2967, "menghasilkan": 2968, "yng": 2969, "sina": 2970, "kemasannya": 2971, "percepat": 2972, "teman": 2973, "tawaran": 2974, "klok": 2975, "temen": 2976, "sadar": 2977, "bawa": 2978, "seribu": 2979, "penyakit": 2980, "cantumkan": 2981, "pokokny": 2982, "pokokx": 2983, "ooke": 2984, "spya": 2985, "bb": 2986, "kealamat": 2987, "dituju": 2988, "hayoh": 2989, "ngaganggu": 2990, "teu": 2991, "siah": 2992, "zwwcuugty": 2993, "adaaa": 2994, "ngagu": 2995, "informasi": 2996, "apalagi": 2997, "efektif": 2998, "bagusssx": 2999, "kehendak": 3000, "penggunaan": 3001, "amburadul": 3002, "kenapa": 3003, "jne": 3004, "tiki": 3005, "exspres": 3006, "milik": 3007, "yang": 3008, "mantaaaaf": 3009, "maken": 3010, "semuga": 3011, "menjaga": 3012, "kepercayaan": 3013, "mempercayai": 3014, "drastis": 3015, "fasilitas": 3016, "pensiunan": 3017, "pensiun": 3018, "vocernya": 3019, "citer": 3020, "epep": 3021, "selamat": 3022, "payment": 3023, "kredeit": 3024, "debit": 3025, "jnecargo": 3026, "2minggu": 3027, "lebih": 3028, "shoping": 3029, "ibu2": 3030, "sr": 3031, "fezxezccxt": 3032, "xc": 3033, "nyelesain": 3034, "sumpa": 3035, "jore": 3036, "bsadipakai": 3037, "gil": 3038, "begeteee": 3039, "haus": 3040, "novel": 3041, "945perak": 3042, "alhamdullilah": 3043, "sp": 3044, "cairin": 3045, "bolehh": 3046, "mendig": 3047, "mantaap": 3048, "hadiaahnyaa": 3049, "woyy": 3050, "jan": 3051, "luu": 3052, "lemod": 3053, "pocer": 3054, "lainnya": 3055, "starseller": 3056, "bener\u00b2": 3057, "kalii": 3058, "biisa": 3059, "1jam": 3060, "tiidak": 3061, "adiil": 3062, "sayangkan": 3063, "kebiijakan": 3064, "merugiikan": 3065, "cokout": 3066, "lamaaaaaaaaaa": 3067, "lamaaaa": 3068, "saingan": 3069, "affiliator": 3070, "susah2": 3071, "viewers": 3072, "diturunin": 3073, "promosi": 3074, "diawal": 3075, "lanjiaolah": 3076, "chawnima": 3077, "peh": 3078, "njnjm": 3079, "well": 3080, "10k": 3081, "gambang": 3082, "juga\ud83d\udc4d": 3083, "narik": 3084, "1juta": 3085, "rek": 3086, "\ud83d\ude14\ud83d\ude14\ud83d\ude14\ud83d\ude14": 3087, "tiket": 3088, "pesawat": 3089, "pemgembalian": 3090, "tikey": 3091, "nenyesal": 3092, "banget\ud83d\ude0d\ud83d\ude0d": 3093, "lancio": 3094, "bgt\ud83d\ude0d\ud83d\ude0d\ud83d\ude0d\ud83d\ude0d\ud83d\ude0d\ud83d\ude0d\ud83d\ude0d\ud83d\ude01\ud83d\ude0d\ud83d\ude0d\ud83d\ude0d\u2764\ud83d\ude0d\ud83d\ude0d\u2764\ud83d\ude0d\ud83d\ude0d\ud83d\ude0d\ud83d\ude0d\u2764\ud83d\ude0d\ud83d\ude0d\ud83d\ude0d\ud83d\ude0d\ud83d\ude0d\ud83d\ude0d\ud83d\ude0d\ud83d\ude0d\ud83d\ude0d\ud83d\ude0d\u2764\u2764\u2764\u2764\u2764\ud83e\udd19\ud83d\ude0d\ud83e\udd19\ud83d\ude0d\ud83d\ude0d\ud83e\udd19\ud83d\ude0d\ud83e\udd19\ud83e\udd19\ud83d\ude0d\ud83e\udd19\ud83d\ude0d\ud83d\ude0d\ud83e\udd19\ud83d\ude0d\ud83e\udd19\ud83d\ude0d\ud83e\udd19\ud83d\ude0d\ud83d\ude0d\ud83d\ude0d\ud83d\ude0d\ud83e\udd19\ud83d\ude0d\ud83e\udd19\ud83e\udd19\ud83d\ude0d\ud83e\udd19\ud83d\ude0d": 3095, "muaaaaaantaf": 3096, "isi2": 3097, "ibarat": 3098, "tingjatkan": 3099, "\u2764\u2764": 3100, "manuk": 3101, "kan\ud83d\ude24\ud83d\ude24": 3102, "impian": 3103, "menghema": 3104, "pulih": 3105, "sayah": 3106, "menunjang": 3107, "profit": 3108, "hangusnya": 3109, "diluar": 3110, "pergi2": 3111, "minn": 3112, "mantappppppp": 3113, "relevan": 3114, "kbnyakan": 3115, "transit": 3116, "\ud83d\ude05": 3117, "\ud83d\ude4f\ud83c\udffb": 3118, "situ": 3119, "tertulis": 3120, "sekian\u00b2": 3121, "aap": 3122, "dicoba": 3123, "lcr": 3124, "gartis": 3125, "cantik": 3126, "akibat": 3127, "dikemballikan": 3128, "sabar": 3129, "open": 3130, "lapak": 3131, "\ud83e\udec2": 3132, "\ud83d\ude2b": 3133, "2000": 3134, "angka": 3135, "50000": 3136, "ngigau": 3137, "mari": 3138, "curangnya": 3139, "40": 3140, "mah": 3141, "berusah": 3142, "mengurangi": 3143, "aktif\ud83e\udd7a": 3144, "se": 3145, "jossss\ud83d\udc4d\ud83d\udc4d\ud83d\udc4d": 3146, "ja": 3147, "review": 3148, "mengeluh": 3149, "pastikan": 3150, "cair": 3151, "porno": 3152, "aksi": 3153, "menyadari": 3154, "bokkep": 3155, "perkecil": 3156, "berhubungan": 3157, "erat": 3158, "instan": 3159, "koja": 3160, "jakut": 3161, "jaktim": 3162, "dki": 3163, "shopiee": 3164, "celana": 3165, "rijek": 3166, "31": 3167, "32": 3168, "nihil": 3169, "sunquick": 3170, "orange": 3171, "juss": 3172, "pernikahan": 3173, "jkt": 3174, "borma": 3175, "mengeluarkan": 3176, "nominal": 3177, "broo": 3178, "kesalahan": 3179, "sampai\u263a\ufe0f": 3180, "47up": 3181, "ce": 3182, "stuff": 3183, "r": 3184, "mal": 3185, "berhari2": 3186, "antar2": 3187, "bisaa": 3188, "muluu": 3189, "peminat": 3190, "qqqaqqqqqq": 3191, "lamaaaaa": 3192, "benerrrrr": 3193, "serahkan": 3194, "lumutan": 3195, "utuh": 3196, "payahhhhhhh": 3197, "vape": 3198, "dipencarian": 3199, "dananya": 3200, "atuh": 3201, "rezekinya": 3202, "shopee\ud83d\ude01\ud83d\ude01": 3203, "utamakan": 3204, "cegah": 3205, "klw": 3206, "kesaya": 3207, "amiin": 3208, "xpress": 3209, "biarpun": 3210, "reguler": 3211, "dinyatakan": 3212, "dak": 3213, "sanggup": 3214, "\ud83d\ude02593o": 3215, "iklannn": 3216, "anjingg": 3217, "nakal2": 3218, "baned": 3219, "tamabahin": 3220, "mendaftar": 3221, "bebelanja": 3222, "gambarnya": 3223, "mangatap": 3224, "kurang": 3225, "terlambat": 3226, "\ud83d\udc4e\ud83d\udc4e\ud83d\udc4ebagusan": 3227, "tpat": 3228, "waktu\ud83d\udc4d\ud83d\udc4d\ud83d\udc4d": 3229, "melonjak": 3230, "kerenn\ud83d\ude0d\ud83d\ude0d\ud83c\uddee\ud83c\udde9\ud83c\uddf2\ud83c\udde8\ud83c\uddf2\ud83c\udde8": 3231, "bangga": 3232, "programnya": 3233, "hehehheh": 3234, "parahhh": 3235, "permainan": 3236, "jumalh": 3237, "airnya": 3238, "rumput": 3239, "tetangga": 3240, "yaaa": 3241, "kndala": 3242, "curang": 3243, "qta": 3244, "lapor": 3245, "ttap": 3246, "terpakai": 3247, "\ud83e\udd29": 3248, "gaperna": 3249, "follow": 3250, "dlam": 3251, "tkss": 3252, "zaman": 3253, "degan": 3254, "wey": 3255, "pahit": 3256, "puasa": 3257, "hany": 3258, "4g": 3259, "bosan": 3260, "kebagian": 3261, "ngutang": 3262, "chooyy": 3263, "anjing": 3264, "hal": 3265, "kalok": 3266, "menyedot": 3267, "dar": 3268, "gur": 3269, "sek": 3270, "iso": 3271, "liane": 3272, "ongkire": 3273, "separo": 3274, "comot": 3275, "misteri": 3276, "endingnya": 3277, "kw": 3278, "tembakan": 3279, "36": 3280, "45k": 3281, "budayakan": 3282, "ingatlah": 3283, "pertagung": 3284, "kelebihan": 3285, "hy": 3286, "shophee": 3287, "descripsinya": 3288, "contohnya": 3289, "kipas": 3290, "angin": 3291, "diameter": 3292, "baling\u00b2nya": 3293, "akibatnya": 3294, "consumen": 3295, "tertipu": 3296, "qedsj": 3297, "mantaaaaaaaaaaap": 3298, "troble": 3299, "smakin": 3300, "berencana": 3301, "o": 3302, "trf": 3303, "godd\ud83e\udd70\ud83e\udd70\ud83d\udc4d\ud83d\udc4d\ud83d\udc4d\u2b50\u2b50\u2b50\u2b50\u2b50\u2b50\u2b50\u2b50\u2b50\u2b50\u2b50\u2b50\u2b50\u2b50\u2b50\u2b50": 3304, "mening": 3305, "senam": 3306, "affiliate": 3307, "bner2": 3308, "hadehhhh": 3309, "capit": 3310, "capitan": 3311, "saingannya": 3312, "geratis": 3313, "sainganya": 3314, "6000": 3315, "jabodetabek": 3316, "telkomsel": 3317, "uy": 3318, "dibodohi": 3319, "jelas2": 3320, "menara": 3321, "koneksinya": 3322, "cekot": 3323, "masukkin": 3324, "telepon": 3325, "hehe\u2764\ufe0f": 3326, "knpp": 3327, "pass": 3328, "kluar": 3329, "nomre": 3330, "dhal": 3331, "gmnh": 3332, "mood": 3333, "mantappppp": 3334, "maksudnyaa": 3335, "begini": 3336, "ribuan": 3337, "soalnya": 3338, "istimewaaa": 3339, "dishoppe": 3340, "bedahkan": 3341, "korban": 3342, "kemana\u00b2": 3343, "ditipu": 3344, "ngecewain": 3345, "acungi": 3346, "celurit": 3347, "luar": 3348, "umpan": 3349, "pancing": 3350, "casting": 3351, "dibikin": 3352, "dikenakan": 3353, "meningkatkan": 3354, "layanannya": 3355, "mantaaff": 3356, "tambahin": 3357, "bedah": 3358, "begitu": 3359, "leletnya": 3360, "perbaikan": 3361, "ajib\ud83d\udc4c\ud83c\udfff\ud83c\udf3b\ud83d\ude4f\ud83c\udfff": 3362, "mengcewa": 3363, "ganguan": 3364, "masih": 3365, "sebenarnya": 3366, "kesannya": 3367, "kasihan": 3368, "ngumpul": 3369, "hanya": 3370, "trsbt": 3371, "black": 3372, "list": 3373, "joossssss": 3374, "mantabbbb": 3375, "updete": 3376, "kg": 3377, "menambah": 3378, "keunggulan": 3379, "redupin\ud83d\ude4f": 3380, "terlangganan": 3381, "budget": 3382, "mnyap": 3383, "2\u00d7": 3384, "sekarang\ud83d\ude1e": 3385, "smpe2": 3386, "\ud83d\ude4f\ud83d\ude4f": 3387, "puassss": 3388, "luamayan": 3389, "ongkie": 3390, "hubungkan": 3391, "ah": 3392, "pn": 3393, "loss": 3394, "bin": 3395, "1212": 3396, "mantaaaapz": 3397, "rekomended": 3398, "inii": 3399, "sepenuhnya": 3400, "tgl\u00b2": 3401, "ganggung": 3402, "dilayar": 3403, "gratongnya": 3404, "voc": 3405, "kk\ud83d\ude01": 3406, "cacatt": 3407, "masukk": 3408, "nyimpan": 3409, "milyarann": 3410, "tracking": 3411, "pkaiii": 3412, "masing2": 3413, "camkan": 3414, "ngerti": 3415, "wdeh": 3416, "wkwkkwwk": 3417, "2020": 3418, "selain": 3419, "clba": 3420, "ngedadak": 3421, "upgrade": 3422, "googlenya": 3423, "gmailnya": 3424, "bennnnnnnnnnar": 3425, "tammmmmmmmmmmmmmmmba": 3426, "binnnnnnnn5annnnnng": 3427, "mode": 3428, "gelap": 3429, "silau": 3430, "background": 3431, "digunakan": 3432, "ribeeett": 3433, "ditoktok": 3434, "toktokshop": 3435, "pngajuan": 3436, "uniinstal": 3437, "mencaci": 3438, "maki": 3439, "tokohnya": 3440, "senilai": 3441, "1juta200": 3442, "casd": 3443, "ngaruhnya": 3444, "\ud83d\ude12": 3445, "belanjha": 3446, "belum\ud83d\ude21": 3447, "berkurang\ud83d\ude21\ud83d\ude21": 3448, "nyata": 3449, "prank": 3450, "jossssss": 3451, "parahh": 3452, "seolah": 3453, "kepencet": 3454, "misallnya": 3455, "tua": 3456, "bagussssszzz": 3457, "setiap": 3458, "mengunakan": 3459, "interface": 3460, "haddeeehh": 3461, "keberatan": 3462, "\ud83d\udc4e\ud83d\udc4e\ud83d\udc4e": 3463, "selangit": 3464, "hebohh": 3465, "warga": 3466, "jm": 3467, "aut": 3468, "mampus": 3469, "mantaaaaap": 3470, "datanya": 3471, "perlihatkan": 3472, "buktinya": 3473, "sofie": 3474, "penilaiannnya": 3475, "sarang": 3476, "banyaknya": 3477, "anteng2": 3478, "adminya": 3479, "koplak": 3480, "jaminan": 3481, "meledag": 3482, "koyo": 3483, "pmrsan": 3484, "cumn": 3485, "kaos": 3486, "segla": 3487, "mcem": 3488, "berat2": 3489, "bnet": 3490, "memkan": 3491, "apliksi": 3492, "banyk": 3493, "mngurs": 3494, "tolng": 3495, "kcil": 3496, "taiiii": 3497, "gbsa": 3498, "gitu2": 3499, "selesai2": 3500, "peduli": 3501, "terdepan": 3502, "hyl": 3503, "mr": 3504, "mrs": 3505, "y\ud83d\ude42": 3506, "daptar": 3507, "memesan": 3508, "bisadi": 3509, "viionya": 3510, "marhaban": 3511, "romadon": 3512, "kepake": 3513, "hanguss": 3514, "tadi": 3515, "berinteraksi": 3516, "mimat": 3517, "berbeda": 3518, "bagi2": 3519, "sering2": 3520, "mudah2an": 3521, "rezeki": 3522, "expired": 3523, "seh": 3524, "ngklik": 3525, "dikeranjang": 3526, "birunya": 3527, "diklik": 3528, "freong": 3529, "rupian": 3530, "7rb": 3531, "paraaahhhh": 3532, "menolong": 3533, "tulisannya": 3534, "'gratis": 3535, "rupiah'": 3536, "membantuu\ud83e\udd17": 3537, "casback": 3538, "90k": 3539, "4k": 3540, "plas": 3541, "630k": 3542, "14k": 3543, "620": 3544, "vocer2": 3545, "curiga": 3546, "anneh": 3547, "nongol": 3548, "terpuaskan": 3549, "sayank": 3550, "lemmout": 3551, "brng": 3552, "jargax": 3553, "sni": 3554, "diaktifkan": 3555, "bntar": 3556, "hampir": 3557, "\ud83e\udee4": 3558, "nice\ud83d\udc4d\ud83c\udfff\ud83d\udc4d\ud83c\udfff\ud83d\udc4d\ud83c\udfff\ud83d\udc4d\ud83c\udfff": 3559, "bisah": 3560, "kesempatan": 3561, "keraguan": 3562, "membandel": 3563, "akun2": 3564, "evod": 3565, "anjinggg": 3566, "cacat": 3567, "minggat": 3568, "unggul": 3569, "bndingkn": 3570, "kli": 3571, "engk": 3572, "kenpq": 3573, "ky": 3574, "sebenernya": 3575, "lshh": 3576, "ceperan": 3577, "nutup": 3578, "talangan": 3579, "\ud83d\ude00\ud83d\ude44": 3580, "pngn": 3581, "jln": 3582, "block\ud83d\ude2d\ud83d\ude2d": 3583, "sukaaaaaaa": 3584, "tholol": 3585, "taikucing": 3586, "alikasi": 3587, "ketulungan": 3588, "\ud83d\udcaf": 3589, "pelitttt": 3590, "voucerr": 3591, "huuuu": 3592, "peliiitt": 3593, "kyak": 3594, "pemanis": 3595, "mimpi": 3596, "hihihii": 3597, "siti": 3598, "sa'adah": 3599, "inti": 3600, "nek": 3601, "onok": 3602, "mboh": 3603, "iki": 3604, "opo": 3605, "wes": 3606, "moro": 3607, "entek": 3608, "barange": 3609, "iku": 3610, "jenenge": 3611, "gatel": 3612, "goblok": 3613, "pie": 3614, "duso": 3615, "mbujuk": 3616, "sak": 3617, "entenono": 3618, "azab": 3619, "gawe": 3620, "kabeh": 3621, "titenono": 3622, "\u00b2\u2075\u2070": 3623, "\u2070\u2070\u2070": 3624, "rata\u00b2": 3625, "ndk": 3626, "yuts": 3627, "shhopy": 3628, "gegara": 3629, "diupgrade": 3630, "deras": 3631, "kouta\ud83d\ude05\ud83d\ude05\ud83d\ude05": 3632, "puzzle": 3633, "koperatif": 3634, "hilangin": 3635, "puzzlenya": 3636, "taikkk": 3637, "ngeframe": 3638, "gausa": 3639, "kucing": 3640, "settingan": 3641, "\ud83d\udd95": 3642, "pembodohan": 3643, "\ud83d\ude19ubah": 3644, "\ud83d\ude17": 3645, "terkait": 3646, "dasar": 3647, "dapat": 3648, "boongan": 3649, "servicenya": 3650, "fffx": 3651, "okkkkkkmmljkkkkk": 3652, "ipoh": 3653, "lmao": 3654, "i'm": 3655, "xxx": 3656, "\u20ac": 3657, "xx\u20achigh": 3658, "cvs": 3659, "dc0xdffff": 3660, "dtggkatin": 3661, "kayaknya": 3662, "vicer": 3663, "bevas": 3664, "denda": 3665, "pketku": 3666, "stck": 3667, "keong": 3668, "alami": 3669, "ngaktifin": 3670, "ngaktif": 3671, "4kali": 3672, "bukan": 3673, "ancur": 3674, "parahhhh": 3675, "respon\ud83d\ude22": 3676, "penawaran": 3677, "menggagalkan": 3678, "digagalkan": 3679, "dipulangkan": 3680, "kepihak": 3681, "engapo": 3682, "ngentod": 3683, "ente": 3684, "tanggung": 3685, "inisiatif": 3686, "pecat": 3687, "perhitungkan": 3688, "harinya": 3689, "aduh": 3690, "tolongl": 3691, "matilah": 3692, "45ribu": 3693, "padalah": 3694, "ceckout": 3695, "menyebalkan": 3696, "gateli": 3697, "\ud83d\udc4e\ud83d\udc4e": 3698, "wkkq": 3699, "memudahkn": 3700, "dngn": 3701, "pelaynn": 3702, "reel": 3703, "mantaff": 3704, "pruduk": 3705, "baiknya": 3706, "sempet": 3707, "pkai": 3708, "5bln": 3709, "marikita": 3710, "ketiktok": 3711, "umkm": 3712, "merdeka": 3713, "\ud83e\udd23\ud83d\ude05\ud83d\ude05\ud83c\uddf2\ud83c\udde8\ud83c\uddf2\ud83c\udde8\ud83c\uddf2\ud83c\udde8\ud83c\uddf2\ud83c\udde8": 3714, "lain2nya": 3715, "galaku": 3716, "gausah": 3717, "skip": 3718, "kaga": 3719, "mahalnya": 3720, "jga": 3721, "bedanya": 3722, "bangwt": 3723, "kik": 3724, "kira2": 3725, "ngelebihin": 3726, "infonya": 3727, "brand": 3728, "bp": 3729, "acumalaka": 3730, "heheheha": 3731, "senag": 3732, "nyah": 3733, "bangusss": 3734, "membatuu": 3735, "banggt": 3736, "donlod": 3737, "terhormat": 3738, "menggagu": 3739, "cewe": 3740, "pacar": 3741, "ngambek": 3742, "maya": 3743, "gituan": 3744, "endors": 3745, "kondisi": 3746, "pengirim": 3747, "\ud83d\ude00": 3748, "sana": 3749, "ongki": 3750, "bad": 3751, "experience": 3752, "ditunggu": 3753, "direturn": 3754, "terlaris": 3755, "\ud83d\udc4d\ud83c\udffb\ud83d\udc4d\ud83c\udffb\ud83d\udc4d\ud83c\udffb": 3756, "ngeleg\ud83d\udc4d\ud83d\udc4d\ud83d\udc4d": 3757, "woyyy": 3758, "\ud83d\ude02\ud83d\ude02": 3759, "ongkirny": 3760, "adehhh": 3761, "refresh": 3762, "berkali": 3763, "sory": 3764, "gd": 3765, "gedeg": 3766, "berhati": 3767, "mengirim": 3768, "\ud83d\udc4d\ud83d\ude4f\ud83d\ude18": 3769, "suk": 3770, "dingin": 3771, "thank's": 3772, "kurangin": 3773, "ngerasa": 3774, "disiapkan": 3775, "bangetttt": 3776, "apkikasi": 3777, "cara": 3778, "pg": 3779, "lewt": 3780, "fb": 3781, "hk": 3782, "kenal": 3783, "matur": 3784, "suwun": 3785, "mengejar": 3786, "viral": 3787, "konten": 3788, "sensual": 3789, "beranda": 3790, "kategori": 3791, "dimaksud": 3792, "nyrimpetiii": 3793, "babgett": 3794, "kusan": 3795, "hilir": 3796, "barng": 3797, "laptop": 3798, "57000ribu": 3799, "40000ribu": 3800, "17ribu": 3801, "syng": 3802, "silat": 3803, "pikir": 3804, "rebahan": 3805, "momen": 3806, "bunga": 3807, "letter": 3808, "barang\u00b2": 3809, "kulukulikulik": 3810, "sukai": 3811, "pemesanannya": 3812, "goodd": 3813, "menanjak": 3814, "kebawah": 3815, "penting": 3816, "keuangannya": 3817, "pisahin": 3818, "cerdas": 3819, "pengembang": 3820, "kalian": 3821, "wah": 3822, "gulung": 3823, "tikar": 3824, "gooooodddd": 3825, "naek2": 3826, "spinjem": 3827, "naek3": 3828, "tempo": 3829, "ngelag\u00b2": 3830, "ti": 3831, "kmpg": 3832, "tdi": 3833, "mlm": 3834, "00": 3835, "ta": 3836, "kog": 3837, "stiap": 3838, "sedang": 3839, "downloading": 3840, "ditungguin": 3841, "bs2": 3842, "\ud83e\udd27": 3843, "terbatas": 3844, "ditutup": 3845, "shopper": 3846, "arahan": 3847, "dm": 3848, "ig": 3849, "gajadi": 3850, "bngat": 3851, "sekarng": 3852, "egga": 3853, "buagus": 3854, "scroll2": 3855, "bersyukur": 3856, "mau": 3857, "perna": 3858, "rutenya": 3859, "samanya": 3860, "baik\ud83d\ude4f\ud83d\ude4f\ud83d\ude4f\ud83d\ude4f\ud83d\ude4f": 3861, "stuck": 3862, "bintangnya": 3863, "50rb": 3864, "batasin": 3865, "aaasu": 3866, "ye": 3867, "sme": 3868, "\ud83d\ude43\ud83d\ude43\ud83d\ude43nanti": 3869, "siluman": 3870, "hati2": 3871, "alasannya": 3872, "tau\u00b2": 3873, "membutuh": 3874, "membuka": 3875, "ongkirr": 3876, "betuusss": 3877, "buruan": 3878, "donwlod": 3879, "mungkin": 3880, "cobalah": 3881, "\ud83d\ude4f\ud83d\ude4f\ud83d\ude4f\ud83d\ude4f\ud83d\ude4f\ud83d\ude4f": 3882, "krang": 3883, "krena": 3884, "discont": 3885, "oit": 3886, "emosi": 3887, "gara\u00b9": 3888, "dah\u00b9": 3889, "mls": 3890, "mantap\ud83d\udc4d\ud83d\udc4d\ud83d\udc4d": 3891, "alat": 3892, "speartpat": 3893, "kendaraan": 3894, "hubungan": 3895, "toped": 3896, "ruwet": 3897, "mewah": 3898, "shofee": 3899, "upaya": 3900, "ngapa\u00b2in": 3901, "sekedar": 3902, "info": 3903, "manjemen": 3904, "shp": 3905, "hrus": 3906, "bljr": 3907, "ngebuang": 3908, "dipersulit": 3909, "sama2": 3910, "nguntungin": 3911, "shopee\ud83d\ude07": 3912, "bonusnya": 3913, "teru": 3914, "dancok": 3915, "gratong": 3916, "fix": 3917, "ttshop": 3918, "kbutuhan": 3919, "zivanna": 3920, "sosmed": 3921, "gikiran": 3922, "anjingggg": 3923, "loginnya": 3924, "pad": 3925, "carinya": 3926, "pajak": 3927, "keuntungannya": 3928, "penjua": 3929, "sihl": 3930, "bensin": 3931, "labanya": 3932, "mahal\u00b2": 3933, "sepi": 3934, "tekor": 3935, "sellernya": 3936, "pngembalian": 3937, "tanggapi": 3938, "benci": 3939, "ecommerce": 3940, "salae": 3941, "gagalin": 3942, "perak": 3943, "psanan": 3944, "bersumpah": 3945, "pidah": 3946, "eccomerce": 3947, "tukang": 3948, "ikutan": 3949, "serba12ribu": 3950, "server": 3951, "poli": 3952, "prcaya": 3953, "12rb": 3954, "ketipu": 3955, "reseller": 3956, "kedepane": 3957, "bklan": 3958, "cman": 3959, "rb\ud83d\ude22\ud83d\ude22\ud83d\ude22": 3960, "sulawesi": 3961, "tepatnya": 3962, "marisa": 3963, "hadehh": 3964, "ngecawain": 3965, "west": 3966, "apknya\ud83e\udd7a": 3967, "itu\u00b2": 3968, "jackpot": 3969, "bayat": 3970, ">": 3971, "melanjutkan": 3972, "solusinya": 3973, "bervariatif": 3974, "klop": 3975, "smule": 3976, "mantapppp": 3977, "v": 3978, "terjangakau": 3979, "ekspektasi": 3980, "irit": 3981, "senangx": 3982, "punyaku": 3983, "mo01": 3984, "markotooppp": 3985, "tod": 3986, "tt": 3987, "sok": 3988, "itulah": 3989, "keterangan": 3990, "jooos": 3991, "paylatternya": 3992, "endk": 3993, "mempermudahan": 3994, "izinin": 3995, "bajunya": 3996, "gratuis": 3997, "terinspirasi": 3998, "hih": 3999, "kecewa\ud83d\udc4d": 4000, "dompet": 4001, "disiplin": 4002, "shopee\ud83d\ude4f": 4003, "\ud83d\uddff": 4004, "bestt": 4005, "pergi": 4006, "pasar": 4007, "hrgnya": 4008, "\u263a\ufe0f\ud83d\ude0a": 4009, "cairkan": 4010, "custumer": 4011, "statusnya": 4012, "memng": 4013, "kalangn": 4014, "udin": 4015, "alesan": 4016, "jellas": 4017, "ow": 4018, "iy": 4019, "geser": 4020, "join": 4021, "daya": 4022, "tariknya": 4023, "hitung\u00b2": 4024, "official": 4025, "xixixixixixi": 4026, "bodoh": 4027, "ramh": 4028, "senangnya": 4029, "kecewanya": 4030, "sukanya": 4031, "\u2764\ufe0f\ud83d\udc4d": 4032, "rakyat": 4033, "seleksi": 4034, "sjoopee": 4035, "selamanya": 4036, "santai": 4037, "otak": 4038, "jari": 4039, "kbnykn": 4040, "taii": 4041, "jijik": 4042, "kejutan": 4043, "melaporkan": 4044, "alot": 4045, "melindungi": 4046, "muteeeeer": 4047, "teruus": 4048, "diapdet": 4049, "kalimantan": 4050, "perhatiin": 4051, "naskleng": 4052, "coba2": 4053, "traksaksi": 4054, "bangkek": 4055, "naik2": 4056, "pingin": 4057, "\ud83d\ude44": 4058, "cuma": 4059, "resahkan": 4060, "sekabupaten": 4061, "kurang2ngin": 4062, "don": 4063, "ya\ud83d\ude0a": 4064, "gda": 4065, "polll": 4066, "dulu\ud83d\ude02": 4067, "kebayar": 4068, "spaylaternya": 4069, "cicilan": 4070, "bulanya": 4071, "pembyaran": 4072, "\ud83e\udd23": 4073, "delay": 4074, "mbutuhkan": 4075, "bunda": 4076, "12ribu": 4077, "257jt": 4078, "jati": 4079, "berani": 4080, "terjelek": 4081, "penangan": 4082, "rungsing": 4083, "tersambung": 4084, "merepotkan": 4085, "gaboleh": 4086, "ilangin": 4087, "playstore": 4088, "shooper": 4089, "121223": 4090, "5rebu": 4091, "sedia": 4092, "baran": 4093, "kecepatan": 4094, "close": 4095, "ngirim\ud83d\ude02\ud83e\udd23\ud83d\ude02\ud83e\udd23\ud83d\ude02\ud83e\udd23": 4096, "selagi": 4097, "pilikasih": 4098, "banget\ud83d\udc4e": 4099, "pemakaian": 4100, "wau": 4101, "bangeeett": 4102, "terpecaya\ud83d\udc4d\ud83d\udc4d\ud83d\udc4d": 4103, "\ud83d\udc4d\ud83d\udc4d\ud83d\udc4d\ud83d\ude4f": 4104, "sudarmadi": 4105, "dukun": 4106, "uuhuhuhu": 4107, "hiou": 4108, "po": 4109, "jugak": 4110, "ooooh": 4111, "pye": 4112, "baguuus": 4113, "penonaktifan": 4114, "shoopepaylater": 4115, "dijanjikan": 4116, "hr": 4117, "hri": 4118, "dibobol": 4119, "kmrn": 4120, "ditlp": 4121, "mengatas": 4122, "namakan": 4123, "iming\u00b2": 4124, "mengaktifkan": 4125, "sosro": 4126, "manteepppp": 4127, "kerenn": 4128, "jelet": 4129, "sasaran": 4130, "jalan": 4131, "pedalaman": 4132, "kunci": 4133, "mesti": 4134, "benahi": 4135, "kdang": 4136, "yatim": 4137, "impormasinya": 4138, "syg": 4139, "dobel": 4140, "konusumen": 4141, "kelaparan\ud83d\ude11": 4142, "smnjak": 4143, "smua": 4144, "rmah": 4145, "konter": 4146, "imashartini29": 4147, "sberapa": 4148, "gasss": 4149, "cussss": 4150, "sukaaa": 4151, "sh": 4152, "lg\u00b2": 4153, "bla\u00b2": 4154, "tuk": 4155, "acra": 4156, "gatot": 4157, "smpe\u00b2": 4158, "lwt": 4159, "estimasinya": 4160, "grecep": 4161, "teguran": 4162, "berkali\u00b2\ud83e\udd26": 4163, "slh": 4164, "dikecewakan": 4165, "berkali\u00b2": 4166, "bego'y": 4167, "setalah": 4168, "dimasukkan": 4169, "sumpahin": 4170, "didunia": 4171, "akhirat": 4172, "menyesal": 4173, "\ud83d\udc4d\ud83c\udffc": 4174, "asuuuuuuu": 4175, "sopqn": 4176, "hadeeuh": 4177, "subsidi": 4178, "wuelekkkkk": 4179, "kondisikan": 4180, "keterbelakangan": 4181, "mental": 4182, "aplikasinyaa": 4183, "ganteng": 4184, "jkt48": 4185, "gampabg": 4186, "gopay": 4187, "laszada": 4188}